{
	"_id": "545368049e9a5b60405e79fc",
	"selector": ":root",
	"update_comment": "",
	"ownerId": "",
	"persistence": "none",
	"settings": {
		"postrequestbody": "",
		"authentication": "none",
		"auth_password": "",
		"typerequest": "HTTP_GET",
		"urlrandom": "0",
		"auth_userid": "",
		"url": "http://localhost:3000/dbdriver/mysql/get/classicmodels/customers",
		"dbdriver": "mysql",
		"dbnames": {
			"database": "classicmodels",
			"collection": "customers"
		}
	},
	"appexpr": [],
	"format": "json",
	"dependency": "",
	"category": "",
	"description": "MYSQL Get Orders For Customer using 2 queries",
	"name": "qGetOrdersByName",
	"connector": "http",
	"requestDate": "2014-10-31T19:40:33.895Z",
	"parameters": [
		{
			"name": "ContactLastName",
			"type": "",
			"value": "King",
			"operation": "eq"
		},
		{
			"name": "ContactFirstName",
			"type": "",
			"value": "Jean",
			"operation": "eq"
		}
	],
	"metadata": "{\"name\":\"root\",\"type\":\"root\",\"children\":{\"orderNumber\":{\"name\":\"orderNumber\",\"type\":\"Number\",\"options\":{\"properties\":{},\"gcontrols\":[{\"name\":\"SimpleText\",\"perspective\":\"Default\",\"type\":\"TextField\",\"attributes\":{\"label\":\"orderNumber\"},\"styles\":{}},{\"name\":\"SimpleEdit\",\"perspective\":\"Edit\",\"type\":\"TextField\",\"attributes\":{\"label\":\"orderNumber\"},\"styles\":{}}]},\"children\":{}},\"orderDate\":{\"name\":\"orderDate\",\"type\":\"String\",\"options\":{\"properties\":{},\"gcontrols\":[{\"name\":\"SimpleText\",\"perspective\":\"Default\",\"type\":\"TextField\",\"attributes\":{\"label\":\"orderDate\"},\"styles\":{}},{\"name\":\"SimpleEdit\",\"perspective\":\"Edit\",\"type\":\"TextField\",\"attributes\":{\"label\":\"orderDate\"},\"styles\":{}}]},\"children\":{}},\"requiredDate\":{\"name\":\"requiredDate\",\"type\":\"String\",\"options\":{\"properties\":{},\"gcontrols\":[{\"name\":\"SimpleText\",\"perspective\":\"Default\",\"type\":\"TextField\",\"attributes\":{\"label\":\"requiredDate\"},\"styles\":{}},{\"name\":\"SimpleEdit\",\"perspective\":\"Edit\",\"type\":\"TextField\",\"attributes\":{\"label\":\"requiredDate\"},\"styles\":{}}]},\"children\":{}},\"shippedDate\":{\"name\":\"shippedDate\",\"type\":\"String\",\"options\":{\"properties\":{},\"gcontrols\":[{\"name\":\"SimpleText\",\"perspective\":\"Default\",\"type\":\"TextField\",\"attributes\":{\"label\":\"shippedDate\"},\"styles\":{}},{\"name\":\"SimpleEdit\",\"perspective\":\"Edit\",\"type\":\"TextField\",\"attributes\":{\"label\":\"shippedDate\"},\"styles\":{}}]},\"children\":{}},\"status\":{\"name\":\"status\",\"type\":\"String\",\"options\":{\"properties\":{},\"gcontrols\":[{\"name\":\"SimpleText\",\"perspective\":\"Default\",\"type\":\"TextField\",\"attributes\":{\"label\":\"status\"},\"styles\":{}},{\"name\":\"SimpleEdit\",\"perspective\":\"Edit\",\"type\":\"TextField\",\"attributes\":{\"label\":\"status\"},\"styles\":{}}]},\"children\":{}},\"comments\":{\"name\":\"comments\",\"type\":\"String\",\"options\":{\"properties\":{},\"gcontrols\":[{\"name\":\"SimpleText\",\"perspective\":\"Default\",\"type\":\"TextField\",\"attributes\":{\"label\":\"comments\"},\"styles\":{}},{\"name\":\"SimpleEdit\",\"perspective\":\"Edit\",\"type\":\"TextField\",\"attributes\":{\"label\":\"comments\"},\"styles\":{}}]},\"children\":{}},\"customerNumber\":{\"name\":\"customerNumber\",\"type\":\"Number\",\"options\":{\"properties\":{},\"gcontrols\":[{\"name\":\"SimpleText\",\"perspective\":\"Default\",\"type\":\"TextField\",\"attributes\":{\"label\":\"customerNumber\"},\"styles\":{}},{\"name\":\"SimpleEdit\",\"perspective\":\"Edit\",\"type\":\"TextField\",\"attributes\":{\"label\":\"customerNumber\"},\"styles\":{}}]},\"children\":{}}}}",
	"source": "db",
	"visibility": "visible",
	"lock": {
		"status": "unlocked"
	},
	"precode": [],
	"postcode": [
		{
			"name": "",
			"code": "cstnum = response.data[0].customerNumber;\n\nexecuteQuery({\"qName\":\"qGetOrders\",\"params\":{\"customerNumber\":cstnum}}, function(res){\n    response=res.data\n    terminateFilter();\n});\n"
		}
	],
	"service": {
		"name": "",
		"method": ""
	},
	"versioning": {
		"my_dfx_db": {
			"last_action": "1425481900",
			"status": "committed",
			"user": "admin"
		},
		"SampleGallery": {
			"last_action": "1424701856",
			"status": "committed",
			"user": "admin"
		},
		"dreamface2": {
			"last_action": "1422542417",
			"status": "committed",
			"user": "admin"
		},
		"dreamface1": {
			"last_action": "1422532642",
			"status": "committed",
			"user": "admin"
		},
		"MyDfApp": {
			"last_action": "1415028292",
			"status": "committed",
			"user": "admin"
		}
	}
}