{
	"_id": "54e61174c3a184786ba8805d",
	"src": "{\n\t\"properties\": {\n\t\t\"title\": {\n\t\t\t\"label\": \"\",\n\t\t\t\"visible\": false,\n\t\t\t\"color\": \"\"\n\t\t},\n\t\t\"tools\": {\n\t\t\t\"color\": false,\n\t\t\t\"edit\": false,\n\t\t\t\"collapse\": false,\n\t\t\t\"fullscreen\": false,\n\t\t\t\"delete\": false\n\t\t},\n\t\t\"sortable\": false\n\t},\n\t\"definition\": [\n\t\t{\n\t\t\t\"id\": \"root\",\n\t\t\t\"type\": \"panel\",\n\t\t\t\"attributes\": {\n\t\t\t\t\"name\": {\n\t\t\t\t\t\"value\": \"pnlPanel1\"\n\t\t\t\t},\n\t\t\t\t\"controller\": {\n\t\t\t\t\t\"value\": \"wWatsonPIController\"\n\t\t\t\t},\n\t\t\t\t\"form\": {\n\t\t\t\t\t\"value\": \"wWatsonPIForm\"\n\t\t\t\t},\n\t\t\t\t\"model\": {\n\t\t\t\t\t\"value\": \"\"\n\t\t\t\t},\n\t\t\t\t\"useModel\": {\n\t\t\t\t\t\"value\": false\n\t\t\t\t},\n\t\t\t\t\"collapsible\": {\n\t\t\t\t\t\"value\": false\n\t\t\t\t},\n\t\t\t\t\"classes\": {\n\t\t\t\t\t\"value\": \"\"\n\t\t\t\t},\n\t\t\t\t\"display\": {\n\t\t\t\t\t\"value\": \"\"\n\t\t\t\t},\n\t\t\t\t\"title\": {\n\t\t\t\t\t\"value\": \"\"\n\t\t\t\t},\n\t\t\t\t\"titleVisible\": {\n\t\t\t\t\t\"value\": false\n\t\t\t\t},\n\t\t\t\t\"css\": {\n\t\t\t\t\t\"width\": \"\",\n\t\t\t\t\t\"height\": \"\",\n\t\t\t\t\t\"color\": \"\",\n\t\t\t\t\t\"background\": \"\",\n\t\t\t\t\t\"padding\": \"\",\n\t\t\t\t\t\"margin\": \"\",\n\t\t\t\t\t\"text-align\": \"\"\n\t\t\t\t},\n\t\t\t\t\"bodyCss\": {\n\t\t\t\t\t\"width\": \"\",\n\t\t\t\t\t\"height\": \"\",\n\t\t\t\t\t\"color\": \"\",\n\t\t\t\t\t\"background\": \"\",\n\t\t\t\t\t\"padding\": \"\",\n\t\t\t\t\t\"margin\": \"\",\n\t\t\t\t\t\"text-align\": \"\"\n\t\t\t\t},\n\t\t\t\t\"bodyClasses\": {\n\t\t\t\t\t\"value\": \"\"\n\t\t\t\t},\n\t\t\t\t\"bodyDynamicClasses\": {\n\t\t\t\t\t\"value\": \"\"\n\t\t\t\t},\n\t\t\t\t\"style\": {\n\t\t\t\t\t\"value\": \"\"\n\t\t\t\t},\n\t\t\t\t\"layout\": {\n\t\t\t\t\t\"rows\": [\n\t\t\t\t\t\t{\n\t\t\t\t\t\t\t\"cols\": [\n\t\t\t\t\t\t\t\t{\n\t\t\t\t\t\t\t\t\t\"width\": {\n\t\t\t\t\t\t\t\t\t\t\"value\": \"12\"\n\t\t\t\t\t\t\t\t\t},\n\t\t\t\t\t\t\t\t\t\"classes\": {\n\t\t\t\t\t\t\t\t\t\t\"value\": \"jumbotron\"\n\t\t\t\t\t\t\t\t\t},\n\t\t\t\t\t\t\t\t\t\"dynamicClasses\": {\n\t\t\t\t\t\t\t\t\t\t\"value\": \"\"\n\t\t\t\t\t\t\t\t\t},\n\t\t\t\t\t\t\t\t\t\"style\": {\n\t\t\t\t\t\t\t\t\t\t\"value\": \"background-image:url(/resources/Examples/images/ic-who-uses-image-banner.png)\"\n\t\t\t\t\t\t\t\t\t},\n\t\t\t\t\t\t\t\t\t\"orientation\": {\n\t\t\t\t\t\t\t\t\t\t\"value\": \"vertical\"\n\t\t\t\t\t\t\t\t\t},\n\t\t\t\t\t\t\t\t\t\"alignment\": {\n\t\t\t\t\t\t\t\t\t\t\"value\": \"center\"\n\t\t\t\t\t\t\t\t\t},\n\t\t\t\t\t\t\t\t\t\"disposition\": {\n\t\t\t\t\t\t\t\t\t\t\"value\": \"center\"\n\t\t\t\t\t\t\t\t\t},\n\t\t\t\t\t\t\t\t\t\"css\": {\n\t\t\t\t\t\t\t\t\t\t\"color\": \"\",\n\t\t\t\t\t\t\t\t\t\t\"background\": \"\",\n\t\t\t\t\t\t\t\t\t\t\"padding\": \"\",\n\t\t\t\t\t\t\t\t\t\t\"text-align\": \"\"\n\t\t\t\t\t\t\t\t\t}\n\t\t\t\t\t\t\t\t}\n\t\t\t\t\t\t\t],\n\t\t\t\t\t\t\t\"classes\": {\n\t\t\t\t\t\t\t\t\"value\": \"\"\n\t\t\t\t\t\t\t},\n\t\t\t\t\t\t\t\"dynamicClasses\": {\n\t\t\t\t\t\t\t\t\"value\": \"\"\n\t\t\t\t\t\t\t},\n\t\t\t\t\t\t\t\"style\": {\n\t\t\t\t\t\t\t\t\"value\": \"\"\n\t\t\t\t\t\t\t},\n\t\t\t\t\t\t\t\"css\": {\n\t\t\t\t\t\t\t\t\"height\": \"\",\n\t\t\t\t\t\t\t\t\"color\": \"\",\n\t\t\t\t\t\t\t\t\"background\": \"\"\n\t\t\t\t\t\t\t}\n\t\t\t\t\t\t},\n\t\t\t\t\t\t{\n\t\t\t\t\t\t\t\"cols\": [\n\t\t\t\t\t\t\t\t{\n\t\t\t\t\t\t\t\t\t\"width\": {\n\t\t\t\t\t\t\t\t\t\t\"value\": \"4\"\n\t\t\t\t\t\t\t\t\t},\n\t\t\t\t\t\t\t\t\t\"classes\": {\n\t\t\t\t\t\t\t\t\t\t\"value\": \"\"\n\t\t\t\t\t\t\t\t\t},\n\t\t\t\t\t\t\t\t\t\"dynamicClasses\": {\n\t\t\t\t\t\t\t\t\t\t\"value\": \"\"\n\t\t\t\t\t\t\t\t\t},\n\t\t\t\t\t\t\t\t\t\"style\": {\n\t\t\t\t\t\t\t\t\t\t\"value\": \"\"\n\t\t\t\t\t\t\t\t\t},\n\t\t\t\t\t\t\t\t\t\"orientation\": {\n\t\t\t\t\t\t\t\t\t\t\"value\": \"vertical\"\n\t\t\t\t\t\t\t\t\t},\n\t\t\t\t\t\t\t\t\t\"alignment\": {\n\t\t\t\t\t\t\t\t\t\t\"value\": \"start\"\n\t\t\t\t\t\t\t\t\t},\n\t\t\t\t\t\t\t\t\t\"disposition\": {\n\t\t\t\t\t\t\t\t\t\t\"value\": \"space_around\"\n\t\t\t\t\t\t\t\t\t},\n\t\t\t\t\t\t\t\t\t\"css\": {\n\t\t\t\t\t\t\t\t\t\t\"color\": \"\",\n\t\t\t\t\t\t\t\t\t\t\"background\": \"\",\n\t\t\t\t\t\t\t\t\t\t\"padding\": \"\",\n\t\t\t\t\t\t\t\t\t\t\"text-align\": \"\"\n\t\t\t\t\t\t\t\t\t}\n\t\t\t\t\t\t\t\t},\n\t\t\t\t\t\t\t\t{\n\t\t\t\t\t\t\t\t\t\"width\": {\n\t\t\t\t\t\t\t\t\t\t\"value\": \"4\"\n\t\t\t\t\t\t\t\t\t},\n\t\t\t\t\t\t\t\t\t\"classes\": {\n\t\t\t\t\t\t\t\t\t\t\"value\": \"\"\n\t\t\t\t\t\t\t\t\t},\n\t\t\t\t\t\t\t\t\t\"dynamicClasses\": {\n\t\t\t\t\t\t\t\t\t\t\"value\": \"\"\n\t\t\t\t\t\t\t\t\t},\n\t\t\t\t\t\t\t\t\t\"style\": {\n\t\t\t\t\t\t\t\t\t\t\"value\": \"\"\n\t\t\t\t\t\t\t\t\t},\n\t\t\t\t\t\t\t\t\t\"orientation\": {\n\t\t\t\t\t\t\t\t\t\t\"value\": \"vertical\"\n\t\t\t\t\t\t\t\t\t},\n\t\t\t\t\t\t\t\t\t\"alignment\": {\n\t\t\t\t\t\t\t\t\t\t\"value\": \"start\"\n\t\t\t\t\t\t\t\t\t},\n\t\t\t\t\t\t\t\t\t\"disposition\": {\n\t\t\t\t\t\t\t\t\t\t\"value\": \"space_around\"\n\t\t\t\t\t\t\t\t\t},\n\t\t\t\t\t\t\t\t\t\"css\": {\n\t\t\t\t\t\t\t\t\t\t\"color\": \"\",\n\t\t\t\t\t\t\t\t\t\t\"background\": \"\",\n\t\t\t\t\t\t\t\t\t\t\"padding\": \"\",\n\t\t\t\t\t\t\t\t\t\t\"text-align\": \"\"\n\t\t\t\t\t\t\t\t\t}\n\t\t\t\t\t\t\t\t},\n\t\t\t\t\t\t\t\t{\n\t\t\t\t\t\t\t\t\t\"width\": {\n\t\t\t\t\t\t\t\t\t\t\"value\": \"4\"\n\t\t\t\t\t\t\t\t\t},\n\t\t\t\t\t\t\t\t\t\"classes\": {\n\t\t\t\t\t\t\t\t\t\t\"value\": \"\"\n\t\t\t\t\t\t\t\t\t},\n\t\t\t\t\t\t\t\t\t\"dynamicClasses\": {\n\t\t\t\t\t\t\t\t\t\t\"value\": \"\"\n\t\t\t\t\t\t\t\t\t},\n\t\t\t\t\t\t\t\t\t\"style\": {\n\t\t\t\t\t\t\t\t\t\t\"value\": \"\"\n\t\t\t\t\t\t\t\t\t},\n\t\t\t\t\t\t\t\t\t\"orientation\": {\n\t\t\t\t\t\t\t\t\t\t\"value\": \"vertical\"\n\t\t\t\t\t\t\t\t\t},\n\t\t\t\t\t\t\t\t\t\"alignment\": {\n\t\t\t\t\t\t\t\t\t\t\"value\": \"start\"\n\t\t\t\t\t\t\t\t\t},\n\t\t\t\t\t\t\t\t\t\"disposition\": {\n\t\t\t\t\t\t\t\t\t\t\"value\": \"space_around\"\n\t\t\t\t\t\t\t\t\t},\n\t\t\t\t\t\t\t\t\t\"css\": {\n\t\t\t\t\t\t\t\t\t\t\"color\": \"\",\n\t\t\t\t\t\t\t\t\t\t\"background\": \"\",\n\t\t\t\t\t\t\t\t\t\t\"padding\": \"\",\n\t\t\t\t\t\t\t\t\t\t\"text-align\": \"\"\n\t\t\t\t\t\t\t\t\t}\n\t\t\t\t\t\t\t\t}\n\t\t\t\t\t\t\t],\n\t\t\t\t\t\t\t\"classes\": {\n\t\t\t\t\t\t\t\t\"value\": \"\"\n\t\t\t\t\t\t\t},\n\t\t\t\t\t\t\t\"dynamicClasses\": {\n\t\t\t\t\t\t\t\t\"value\": \"\"\n\t\t\t\t\t\t\t},\n\t\t\t\t\t\t\t\"style\": {\n\t\t\t\t\t\t\t\t\"value\": \"\"\n\t\t\t\t\t\t\t},\n\t\t\t\t\t\t\t\"css\": {\n\t\t\t\t\t\t\t\t\"height\": \"\",\n\t\t\t\t\t\t\t\t\"color\": \"\",\n\t\t\t\t\t\t\t\t\"background\": \"\"\n\t\t\t\t\t\t\t}\n\t\t\t\t\t\t},\n\t\t\t\t\t\t{\n\t\t\t\t\t\t\t\"cols\": [\n\t\t\t\t\t\t\t\t{\n\t\t\t\t\t\t\t\t\t\"width\": {\n\t\t\t\t\t\t\t\t\t\t\"value\": \"4\"\n\t\t\t\t\t\t\t\t\t},\n\t\t\t\t\t\t\t\t\t\"classes\": {\n\t\t\t\t\t\t\t\t\t\t\"value\": \"\"\n\t\t\t\t\t\t\t\t\t},\n\t\t\t\t\t\t\t\t\t\"dynamicClasses\": {\n\t\t\t\t\t\t\t\t\t\t\"value\": \"\"\n\t\t\t\t\t\t\t\t\t},\n\t\t\t\t\t\t\t\t\t\"style\": {\n\t\t\t\t\t\t\t\t\t\t\"value\": \"\"\n\t\t\t\t\t\t\t\t\t},\n\t\t\t\t\t\t\t\t\t\"orientation\": {\n\t\t\t\t\t\t\t\t\t\t\"value\": \"vertical\"\n\t\t\t\t\t\t\t\t\t},\n\t\t\t\t\t\t\t\t\t\"alignment\": {\n\t\t\t\t\t\t\t\t\t\t\"value\": \"end\"\n\t\t\t\t\t\t\t\t\t},\n\t\t\t\t\t\t\t\t\t\"disposition\": {\n\t\t\t\t\t\t\t\t\t\t\"value\": \"space_around\"\n\t\t\t\t\t\t\t\t\t},\n\t\t\t\t\t\t\t\t\t\"css\": {\n\t\t\t\t\t\t\t\t\t\t\"color\": \"\",\n\t\t\t\t\t\t\t\t\t\t\"background\": \"\",\n\t\t\t\t\t\t\t\t\t\t\"padding\": \"\",\n\t\t\t\t\t\t\t\t\t\t\"text-align\": \"\"\n\t\t\t\t\t\t\t\t\t}\n\t\t\t\t\t\t\t\t},\n\t\t\t\t\t\t\t\t{\n\t\t\t\t\t\t\t\t\t\"width\": {\n\t\t\t\t\t\t\t\t\t\t\"value\": \"4\"\n\t\t\t\t\t\t\t\t\t},\n\t\t\t\t\t\t\t\t\t\"classes\": {\n\t\t\t\t\t\t\t\t\t\t\"value\": \"\"\n\t\t\t\t\t\t\t\t\t},\n\t\t\t\t\t\t\t\t\t\"dynamicClasses\": {\n\t\t\t\t\t\t\t\t\t\t\"value\": \"\"\n\t\t\t\t\t\t\t\t\t},\n\t\t\t\t\t\t\t\t\t\"style\": {\n\t\t\t\t\t\t\t\t\t\t\"value\": \"\"\n\t\t\t\t\t\t\t\t\t},\n\t\t\t\t\t\t\t\t\t\"orientation\": {\n\t\t\t\t\t\t\t\t\t\t\"value\": \"vertical\"\n\t\t\t\t\t\t\t\t\t},\n\t\t\t\t\t\t\t\t\t\"alignment\": {\n\t\t\t\t\t\t\t\t\t\t\"value\": \"end\"\n\t\t\t\t\t\t\t\t\t},\n\t\t\t\t\t\t\t\t\t\"disposition\": {\n\t\t\t\t\t\t\t\t\t\t\"value\": \"space_around\"\n\t\t\t\t\t\t\t\t\t},\n\t\t\t\t\t\t\t\t\t\"css\": {\n\t\t\t\t\t\t\t\t\t\t\"color\": \"\",\n\t\t\t\t\t\t\t\t\t\t\"background\": \"\",\n\t\t\t\t\t\t\t\t\t\t\"padding\": \"\",\n\t\t\t\t\t\t\t\t\t\t\"text-align\": \"\"\n\t\t\t\t\t\t\t\t\t}\n\t\t\t\t\t\t\t\t},\n\t\t\t\t\t\t\t\t{\n\t\t\t\t\t\t\t\t\t\"width\": {\n\t\t\t\t\t\t\t\t\t\t\"value\": \"4\"\n\t\t\t\t\t\t\t\t\t},\n\t\t\t\t\t\t\t\t\t\"classes\": {\n\t\t\t\t\t\t\t\t\t\t\"value\": \"\"\n\t\t\t\t\t\t\t\t\t},\n\t\t\t\t\t\t\t\t\t\"dynamicClasses\": {\n\t\t\t\t\t\t\t\t\t\t\"value\": \"\"\n\t\t\t\t\t\t\t\t\t},\n\t\t\t\t\t\t\t\t\t\"style\": {\n\t\t\t\t\t\t\t\t\t\t\"value\": \"\"\n\t\t\t\t\t\t\t\t\t},\n\t\t\t\t\t\t\t\t\t\"orientation\": {\n\t\t\t\t\t\t\t\t\t\t\"value\": \"vertical\"\n\t\t\t\t\t\t\t\t\t},\n\t\t\t\t\t\t\t\t\t\"alignment\": {\n\t\t\t\t\t\t\t\t\t\t\"value\": \"end\"\n\t\t\t\t\t\t\t\t\t},\n\t\t\t\t\t\t\t\t\t\"disposition\": {\n\t\t\t\t\t\t\t\t\t\t\"value\": \"space_around\"\n\t\t\t\t\t\t\t\t\t},\n\t\t\t\t\t\t\t\t\t\"css\": {\n\t\t\t\t\t\t\t\t\t\t\"color\": \"\",\n\t\t\t\t\t\t\t\t\t\t\"background\": \"\",\n\t\t\t\t\t\t\t\t\t\t\"padding\": \"\",\n\t\t\t\t\t\t\t\t\t\t\"text-align\": \"\"\n\t\t\t\t\t\t\t\t\t}\n\t\t\t\t\t\t\t\t}\n\t\t\t\t\t\t\t],\n\t\t\t\t\t\t\t\"classes\": {\n\t\t\t\t\t\t\t\t\"value\": \"\"\n\t\t\t\t\t\t\t},\n\t\t\t\t\t\t\t\"dynamicClasses\": {\n\t\t\t\t\t\t\t\t\"value\": \"\"\n\t\t\t\t\t\t\t},\n\t\t\t\t\t\t\t\"style\": {\n\t\t\t\t\t\t\t\t\"value\": \"\"\n\t\t\t\t\t\t\t},\n\t\t\t\t\t\t\t\"css\": {\n\t\t\t\t\t\t\t\t\"height\": \"\",\n\t\t\t\t\t\t\t\t\"color\": \"\",\n\t\t\t\t\t\t\t\t\"background\": \"\"\n\t\t\t\t\t\t\t}\n\t\t\t\t\t\t}\n\t\t\t\t\t],\n\t\t\t\t\t\"classes\": {\n\t\t\t\t\t\t\"value\": \"\"\n\t\t\t\t\t},\n\t\t\t\t\t\"dynamicClasses\": {\n\t\t\t\t\t\t\"value\": \"\"\n\t\t\t\t\t},\n\t\t\t\t\t\"style\": {\n\t\t\t\t\t\t\"value\": \"\"\n\t\t\t\t\t}\n\t\t\t\t}\n\t\t\t},\n\t\t\t\"children\": [\n\t\t\t\t{\n\t\t\t\t\t\"id\": 70394,\n\t\t\t\t\t\"type\": \"statictext\",\n\t\t\t\t\t\"attributes\": {\n\t\t\t\t\t\t\"name\": {\n\t\t\t\t\t\t\t\"value\": \"txtStaticText1\"\n\t\t\t\t\t\t},\n\t\t\t\t\t\t\"bind\": {\n\t\t\t\t\t\t\t\"value\": \"\"\n\t\t\t\t\t\t},\n\t\t\t\t\t\t\"text\": {\n\t\t\t\t\t\t\t\"value\": \"Watson Personality Insights\"\n\t\t\t\t\t\t},\n\t\t\t\t\t\t\"display\": {\n\t\t\t\t\t\t\t\"value\": \"true\"\n\t\t\t\t\t\t},\n\t\t\t\t\t\t\"tooltip\": {\n\t\t\t\t\t\t\t\"value\": \"\"\n\t\t\t\t\t\t},\n\t\t\t\t\t\t\"tooltipPosition\": {\n\t\t\t\t\t\t\t\"value\": \"top\"\n\t\t\t\t\t\t},\n\t\t\t\t\t\t\"counter\": {\n\t\t\t\t\t\t\t\"bind\": {\n\t\t\t\t\t\t\t\t\"value\": \"\"\n\t\t\t\t\t\t\t},\n\t\t\t\t\t\t\t\"onclick\": {\n\t\t\t\t\t\t\t\t\"value\": \"\"\n\t\t\t\t\t\t\t},\n\t\t\t\t\t\t\t\"position\": {\n\t\t\t\t\t\t\t\t\"value\": \"left\"\n\t\t\t\t\t\t\t}\n\t\t\t\t\t\t},\n\t\t\t\t\t\t\"onclick\": {\n\t\t\t\t\t\t\t\"value\": \"\"\n\t\t\t\t\t\t},\n\t\t\t\t\t\t\"classes\": {\n\t\t\t\t\t\t\t\"value\": \"h1\"\n\t\t\t\t\t\t},\n\t\t\t\t\t\t\"dynamicClasses\": {\n\t\t\t\t\t\t\t\"value\": \"\"\n\t\t\t\t\t\t},\n\t\t\t\t\t\t\"style\": {\n\t\t\t\t\t\t\t\"value\": \"\"\n\t\t\t\t\t\t},\n\t\t\t\t\t\t\"css\": {\n\t\t\t\t\t\t\t\"width\": \"\",\n\t\t\t\t\t\t\t\"height\": \"\",\n\t\t\t\t\t\t\t\"color\": \"#ffffff\",\n\t\t\t\t\t\t\t\"background\": \"\",\n\t\t\t\t\t\t\t\"padding\": \"\",\n\t\t\t\t\t\t\t\"margin\": \"\",\n\t\t\t\t\t\t\t\"text-align\": \"\"\n\t\t\t\t\t\t},\n\t\t\t\t\t\t\"containerClasses\": {\n\t\t\t\t\t\t\t\"value\": \"\"\n\t\t\t\t\t\t},\n\t\t\t\t\t\t\"containerDynamicClasses\": {\n\t\t\t\t\t\t\t\"value\": \"\"\n\t\t\t\t\t\t},\n\t\t\t\t\t\t\"containerStyle\": {\n\t\t\t\t\t\t\t\"value\": \"\"\n\t\t\t\t\t\t},\n\t\t\t\t\t\t\"containerCss\": {\n\t\t\t\t\t\t\t\"width\": \"\",\n\t\t\t\t\t\t\t\"height\": \"\",\n\t\t\t\t\t\t\t\"color\": \"\",\n\t\t\t\t\t\t\t\"background\": \"\",\n\t\t\t\t\t\t\t\"padding\": \"\",\n\t\t\t\t\t\t\t\"margin\": \"\",\n\t\t\t\t\t\t\t\"text-align\": \"\"\n\t\t\t\t\t\t}\n\t\t\t\t\t},\n\t\t\t\t\t\"children\": [],\n\t\t\t\t\t\"container\": \"layout_0_row_0_column_0\"\n\t\t\t\t},\n\t\t\t\t{\n\t\t\t\t\t\"id\": 18633,\n\t\t\t\t\t\"type\": \"panel\",\n\t\t\t\t\t\"attributes\": {\n\t\t\t\t\t\t\"name\": {\n\t\t\t\t\t\t\t\"value\": \"pnlPanel12\"\n\t\t\t\t\t\t},\n\t\t\t\t\t\t\"controller\": {\n\t\t\t\t\t\t\t\"value\": \"\"\n\t\t\t\t\t\t},\n\t\t\t\t\t\t\"form\": {\n\t\t\t\t\t\t\t\"value\": \"\"\n\t\t\t\t\t\t},\n\t\t\t\t\t\t\"model\": {\n\t\t\t\t\t\t\t\"value\": \"\"\n\t\t\t\t\t\t},\n\t\t\t\t\t\t\"useModel\": {\n\t\t\t\t\t\t\t\"value\": false\n\t\t\t\t\t\t},\n\t\t\t\t\t\t\"collapsible\": {\n\t\t\t\t\t\t\t\"value\": false\n\t\t\t\t\t\t},\n\t\t\t\t\t\t\"classes\": {\n\t\t\t\t\t\t\t\"value\": \"trans_panel\"\n\t\t\t\t\t\t},\n\t\t\t\t\t\t\"display\": {\n\t\t\t\t\t\t\t\"value\": \"\"\n\t\t\t\t\t\t},\n\t\t\t\t\t\t\"title\": {\n\t\t\t\t\t\t\t\"value\": \"\"\n\t\t\t\t\t\t},\n\t\t\t\t\t\t\"titleVisible\": {\n\t\t\t\t\t\t\t\"value\": false\n\t\t\t\t\t\t},\n\t\t\t\t\t\t\"css\": {\n\t\t\t\t\t\t\t\"width\": \"90%\",\n\t\t\t\t\t\t\t\"height\": \"\",\n\t\t\t\t\t\t\t\"color\": \"\",\n\t\t\t\t\t\t\t\"background\": \"\",\n\t\t\t\t\t\t\t\"padding\": \"\",\n\t\t\t\t\t\t\t\"margin\": \"\",\n\t\t\t\t\t\t\t\"text-align\": \"\"\n\t\t\t\t\t\t},\n\t\t\t\t\t\t\"bodyCss\": {\n\t\t\t\t\t\t\t\"width\": \"100%\",\n\t\t\t\t\t\t\t\"height\": \"\",\n\t\t\t\t\t\t\t\"color\": \"\",\n\t\t\t\t\t\t\t\"background\": \"\",\n\t\t\t\t\t\t\t\"padding\": \"\",\n\t\t\t\t\t\t\t\"margin\": \"0\",\n\t\t\t\t\t\t\t\"text-align\": \"\"\n\t\t\t\t\t\t},\n\t\t\t\t\t\t\"bodyClasses\": {\n\t\t\t\t\t\t\t\"value\": \"\"\n\t\t\t\t\t\t},\n\t\t\t\t\t\t\"bodyDynamicClasses\": {\n\t\t\t\t\t\t\t\"value\": \"\"\n\t\t\t\t\t\t},\n\t\t\t\t\t\t\"style\": {\n\t\t\t\t\t\t\t\"value\": \"\"\n\t\t\t\t\t\t},\n\t\t\t\t\t\t\"layout\": {\n\t\t\t\t\t\t\t\"rows\": [\n\t\t\t\t\t\t\t\t{\n\t\t\t\t\t\t\t\t\t\"classes\": {\n\t\t\t\t\t\t\t\t\t\t\"value\": \"\"\n\t\t\t\t\t\t\t\t\t},\n\t\t\t\t\t\t\t\t\t\"dynamicClasses\": {\n\t\t\t\t\t\t\t\t\t\t\"value\": \"\"\n\t\t\t\t\t\t\t\t\t},\n\t\t\t\t\t\t\t\t\t\"style\": {\n\t\t\t\t\t\t\t\t\t\t\"value\": \"\"\n\t\t\t\t\t\t\t\t\t},\n\t\t\t\t\t\t\t\t\t\"css\": {\n\t\t\t\t\t\t\t\t\t\t\"height\": \"\",\n\t\t\t\t\t\t\t\t\t\t\"color\": \"\",\n\t\t\t\t\t\t\t\t\t\t\"background\": \"\"\n\t\t\t\t\t\t\t\t\t},\n\t\t\t\t\t\t\t\t\t\"cols\": [\n\t\t\t\t\t\t\t\t\t\t{\n\t\t\t\t\t\t\t\t\t\t\t\"width\": {\n\t\t\t\t\t\t\t\t\t\t\t\t\"value\": \"12\"\n\t\t\t\t\t\t\t\t\t\t\t},\n\t\t\t\t\t\t\t\t\t\t\t\"classes\": {\n\t\t\t\t\t\t\t\t\t\t\t\t\"value\": \"trans_panel\"\n\t\t\t\t\t\t\t\t\t\t\t},\n\t\t\t\t\t\t\t\t\t\t\t\"dynamicClasses\": {\n\t\t\t\t\t\t\t\t\t\t\t\t\"value\": \"\"\n\t\t\t\t\t\t\t\t\t\t\t},\n\t\t\t\t\t\t\t\t\t\t\t\"style\": {\n\t\t\t\t\t\t\t\t\t\t\t\t\"value\": \"\"\n\t\t\t\t\t\t\t\t\t\t\t},\n\t\t\t\t\t\t\t\t\t\t\t\"orientation\": {\n\t\t\t\t\t\t\t\t\t\t\t\t\"value\": \"horizontal\"\n\t\t\t\t\t\t\t\t\t\t\t},\n\t\t\t\t\t\t\t\t\t\t\t\"alignment\": {\n\t\t\t\t\t\t\t\t\t\t\t\t\"value\": \"end\"\n\t\t\t\t\t\t\t\t\t\t\t},\n\t\t\t\t\t\t\t\t\t\t\t\"disposition\": {\n\t\t\t\t\t\t\t\t\t\t\t\t\"value\": \"space_between\"\n\t\t\t\t\t\t\t\t\t\t\t},\n\t\t\t\t\t\t\t\t\t\t\t\"css\": {\n\t\t\t\t\t\t\t\t\t\t\t\t\"color\": \"\",\n\t\t\t\t\t\t\t\t\t\t\t\t\"background\": \"\",\n\t\t\t\t\t\t\t\t\t\t\t\t\"padding\": \"10px\",\n\t\t\t\t\t\t\t\t\t\t\t\t\"text-align\": \"\"\n\t\t\t\t\t\t\t\t\t\t\t}\n\t\t\t\t\t\t\t\t\t\t}\n\t\t\t\t\t\t\t\t\t]\n\t\t\t\t\t\t\t\t},\n\t\t\t\t\t\t\t\t{\n\t\t\t\t\t\t\t\t\t\"cols\": [\n\t\t\t\t\t\t\t\t\t\t{\n\t\t\t\t\t\t\t\t\t\t\t\"width\": {\n\t\t\t\t\t\t\t\t\t\t\t\t\"value\": \"12\"\n\t\t\t\t\t\t\t\t\t\t\t},\n\t\t\t\t\t\t\t\t\t\t\t\"classes\": {\n\t\t\t\t\t\t\t\t\t\t\t\t\"value\": \"\"\n\t\t\t\t\t\t\t\t\t\t\t},\n\t\t\t\t\t\t\t\t\t\t\t\"dynamicClasses\": {\n\t\t\t\t\t\t\t\t\t\t\t\t\"value\": \"\"\n\t\t\t\t\t\t\t\t\t\t\t},\n\t\t\t\t\t\t\t\t\t\t\t\"style\": {\n\t\t\t\t\t\t\t\t\t\t\t\t\"value\": \"\"\n\t\t\t\t\t\t\t\t\t\t\t},\n\t\t\t\t\t\t\t\t\t\t\t\"orientation\": {\n\t\t\t\t\t\t\t\t\t\t\t\t\"value\": \"horizontal\"\n\t\t\t\t\t\t\t\t\t\t\t},\n\t\t\t\t\t\t\t\t\t\t\t\"alignment\": {\n\t\t\t\t\t\t\t\t\t\t\t\t\"value\": \"center\"\n\t\t\t\t\t\t\t\t\t\t\t},\n\t\t\t\t\t\t\t\t\t\t\t\"disposition\": {\n\t\t\t\t\t\t\t\t\t\t\t\t\"value\": \"center\"\n\t\t\t\t\t\t\t\t\t\t\t},\n\t\t\t\t\t\t\t\t\t\t\t\"css\": {\n\t\t\t\t\t\t\t\t\t\t\t\t\"color\": \"\",\n\t\t\t\t\t\t\t\t\t\t\t\t\"background\": \"\",\n\t\t\t\t\t\t\t\t\t\t\t\t\"padding\": \"\",\n\t\t\t\t\t\t\t\t\t\t\t\t\"text-align\": \"\"\n\t\t\t\t\t\t\t\t\t\t\t}\n\t\t\t\t\t\t\t\t\t\t}\n\t\t\t\t\t\t\t\t\t],\n\t\t\t\t\t\t\t\t\t\"classes\": {\n\t\t\t\t\t\t\t\t\t\t\"value\": \"\"\n\t\t\t\t\t\t\t\t\t},\n\t\t\t\t\t\t\t\t\t\"dynamicClasses\": {\n\t\t\t\t\t\t\t\t\t\t\"value\": \"\"\n\t\t\t\t\t\t\t\t\t},\n\t\t\t\t\t\t\t\t\t\"style\": {\n\t\t\t\t\t\t\t\t\t\t\"value\": \"\"\n\t\t\t\t\t\t\t\t\t},\n\t\t\t\t\t\t\t\t\t\"css\": {\n\t\t\t\t\t\t\t\t\t\t\"height\": \"\",\n\t\t\t\t\t\t\t\t\t\t\"color\": \"\",\n\t\t\t\t\t\t\t\t\t\t\"background\": \"\"\n\t\t\t\t\t\t\t\t\t}\n\t\t\t\t\t\t\t\t},\n\t\t\t\t\t\t\t\t{\n\t\t\t\t\t\t\t\t\t\"cols\": [\n\t\t\t\t\t\t\t\t\t\t{\n\t\t\t\t\t\t\t\t\t\t\t\"width\": {\n\t\t\t\t\t\t\t\t\t\t\t\t\"value\": \"12\"\n\t\t\t\t\t\t\t\t\t\t\t},\n\t\t\t\t\t\t\t\t\t\t\t\"classes\": {\n\t\t\t\t\t\t\t\t\t\t\t\t\"value\": \"\"\n\t\t\t\t\t\t\t\t\t\t\t},\n\t\t\t\t\t\t\t\t\t\t\t\"dynamicClasses\": {\n\t\t\t\t\t\t\t\t\t\t\t\t\"value\": \"\"\n\t\t\t\t\t\t\t\t\t\t\t},\n\t\t\t\t\t\t\t\t\t\t\t\"style\": {\n\t\t\t\t\t\t\t\t\t\t\t\t\"value\": \"\"\n\t\t\t\t\t\t\t\t\t\t\t},\n\t\t\t\t\t\t\t\t\t\t\t\"orientation\": {\n\t\t\t\t\t\t\t\t\t\t\t\t\"value\": \"horizontal\"\n\t\t\t\t\t\t\t\t\t\t\t},\n\t\t\t\t\t\t\t\t\t\t\t\"alignment\": {\n\t\t\t\t\t\t\t\t\t\t\t\t\"value\": \"center\"\n\t\t\t\t\t\t\t\t\t\t\t},\n\t\t\t\t\t\t\t\t\t\t\t\"disposition\": {\n\t\t\t\t\t\t\t\t\t\t\t\t\"value\": \"center\"\n\t\t\t\t\t\t\t\t\t\t\t},\n\t\t\t\t\t\t\t\t\t\t\t\"css\": {\n\t\t\t\t\t\t\t\t\t\t\t\t\"color\": \"\",\n\t\t\t\t\t\t\t\t\t\t\t\t\"background\": \"\",\n\t\t\t\t\t\t\t\t\t\t\t\t\"padding\": \"\",\n\t\t\t\t\t\t\t\t\t\t\t\t\"text-align\": \"\"\n\t\t\t\t\t\t\t\t\t\t\t}\n\t\t\t\t\t\t\t\t\t\t}\n\t\t\t\t\t\t\t\t\t],\n\t\t\t\t\t\t\t\t\t\"classes\": {\n\t\t\t\t\t\t\t\t\t\t\"value\": \"\"\n\t\t\t\t\t\t\t\t\t},\n\t\t\t\t\t\t\t\t\t\"dynamicClasses\": {\n\t\t\t\t\t\t\t\t\t\t\"value\": \"\"\n\t\t\t\t\t\t\t\t\t},\n\t\t\t\t\t\t\t\t\t\"style\": {\n\t\t\t\t\t\t\t\t\t\t\"value\": \"\"\n\t\t\t\t\t\t\t\t\t},\n\t\t\t\t\t\t\t\t\t\"css\": {\n\t\t\t\t\t\t\t\t\t\t\"height\": \"\",\n\t\t\t\t\t\t\t\t\t\t\"color\": \"\",\n\t\t\t\t\t\t\t\t\t\t\"background\": \"\"\n\t\t\t\t\t\t\t\t\t}\n\t\t\t\t\t\t\t\t},\n\t\t\t\t\t\t\t\t{\n\t\t\t\t\t\t\t\t\t\"cols\": [\n\t\t\t\t\t\t\t\t\t\t{\n\t\t\t\t\t\t\t\t\t\t\t\"width\": {\n\t\t\t\t\t\t\t\t\t\t\t\t\"value\": 12\n\t\t\t\t\t\t\t\t\t\t\t},\n\t\t\t\t\t\t\t\t\t\t\t\"classes\": {\n\t\t\t\t\t\t\t\t\t\t\t\t\"value\": \"\"\n\t\t\t\t\t\t\t\t\t\t\t},\n\t\t\t\t\t\t\t\t\t\t\t\"dynamicClasses\": {\n\t\t\t\t\t\t\t\t\t\t\t\t\"value\": \"\"\n\t\t\t\t\t\t\t\t\t\t\t},\n\t\t\t\t\t\t\t\t\t\t\t\"style\": {\n\t\t\t\t\t\t\t\t\t\t\t\t\"value\": \"\"\n\t\t\t\t\t\t\t\t\t\t\t},\n\t\t\t\t\t\t\t\t\t\t\t\"orientation\": {\n\t\t\t\t\t\t\t\t\t\t\t\t\"value\": \"vertical\"\n\t\t\t\t\t\t\t\t\t\t\t},\n\t\t\t\t\t\t\t\t\t\t\t\"alignment\": {\n\t\t\t\t\t\t\t\t\t\t\t\t\"value\": \"start\"\n\t\t\t\t\t\t\t\t\t\t\t},\n\t\t\t\t\t\t\t\t\t\t\t\"disposition\": {\n\t\t\t\t\t\t\t\t\t\t\t\t\"value\": \"space_around\"\n\t\t\t\t\t\t\t\t\t\t\t},\n\t\t\t\t\t\t\t\t\t\t\t\"css\": {\n\t\t\t\t\t\t\t\t\t\t\t\t\"color\": \"\",\n\t\t\t\t\t\t\t\t\t\t\t\t\"background\": \"\",\n\t\t\t\t\t\t\t\t\t\t\t\t\"padding\": \"\",\n\t\t\t\t\t\t\t\t\t\t\t\t\"text-align\": \"\"\n\t\t\t\t\t\t\t\t\t\t\t}\n\t\t\t\t\t\t\t\t\t\t}\n\t\t\t\t\t\t\t\t\t],\n\t\t\t\t\t\t\t\t\t\"classes\": {\n\t\t\t\t\t\t\t\t\t\t\"value\": \"\"\n\t\t\t\t\t\t\t\t\t},\n\t\t\t\t\t\t\t\t\t\"dynamicClasses\": {\n\t\t\t\t\t\t\t\t\t\t\"value\": \"\"\n\t\t\t\t\t\t\t\t\t},\n\t\t\t\t\t\t\t\t\t\"style\": {\n\t\t\t\t\t\t\t\t\t\t\"value\": \"\"\n\t\t\t\t\t\t\t\t\t},\n\t\t\t\t\t\t\t\t\t\"css\": {\n\t\t\t\t\t\t\t\t\t\t\"height\": \"\",\n\t\t\t\t\t\t\t\t\t\t\"color\": \"\",\n\t\t\t\t\t\t\t\t\t\t\"background\": \"\"\n\t\t\t\t\t\t\t\t\t}\n\t\t\t\t\t\t\t\t},\n\t\t\t\t\t\t\t\t{\n\t\t\t\t\t\t\t\t\t\"cols\": [\n\t\t\t\t\t\t\t\t\t\t{\n\t\t\t\t\t\t\t\t\t\t\t\"width\": {\n\t\t\t\t\t\t\t\t\t\t\t\t\"value\": \"12\"\n\t\t\t\t\t\t\t\t\t\t\t},\n\t\t\t\t\t\t\t\t\t\t\t\"classes\": {\n\t\t\t\t\t\t\t\t\t\t\t\t\"value\": \"\"\n\t\t\t\t\t\t\t\t\t\t\t},\n\t\t\t\t\t\t\t\t\t\t\t\"dynamicClasses\": {\n\t\t\t\t\t\t\t\t\t\t\t\t\"value\": \"\"\n\t\t\t\t\t\t\t\t\t\t\t},\n\t\t\t\t\t\t\t\t\t\t\t\"style\": {\n\t\t\t\t\t\t\t\t\t\t\t\t\"value\": \"\"\n\t\t\t\t\t\t\t\t\t\t\t},\n\t\t\t\t\t\t\t\t\t\t\t\"orientation\": {\n\t\t\t\t\t\t\t\t\t\t\t\t\"value\": \"horizontal\"\n\t\t\t\t\t\t\t\t\t\t\t},\n\t\t\t\t\t\t\t\t\t\t\t\"alignment\": {\n\t\t\t\t\t\t\t\t\t\t\t\t\"value\": \"start\"\n\t\t\t\t\t\t\t\t\t\t\t},\n\t\t\t\t\t\t\t\t\t\t\t\"disposition\": {\n\t\t\t\t\t\t\t\t\t\t\t\t\"value\": \"space_around\"\n\t\t\t\t\t\t\t\t\t\t\t},\n\t\t\t\t\t\t\t\t\t\t\t\"css\": {\n\t\t\t\t\t\t\t\t\t\t\t\t\"color\": \"\",\n\t\t\t\t\t\t\t\t\t\t\t\t\"background\": \"\",\n\t\t\t\t\t\t\t\t\t\t\t\t\"padding\": \"\",\n\t\t\t\t\t\t\t\t\t\t\t\t\"text-align\": \"\"\n\t\t\t\t\t\t\t\t\t\t\t}\n\t\t\t\t\t\t\t\t\t\t}\n\t\t\t\t\t\t\t\t\t],\n\t\t\t\t\t\t\t\t\t\"classes\": {\n\t\t\t\t\t\t\t\t\t\t\"value\": \"\"\n\t\t\t\t\t\t\t\t\t},\n\t\t\t\t\t\t\t\t\t\"dynamicClasses\": {\n\t\t\t\t\t\t\t\t\t\t\"value\": \"\"\n\t\t\t\t\t\t\t\t\t},\n\t\t\t\t\t\t\t\t\t\"style\": {\n\t\t\t\t\t\t\t\t\t\t\"value\": \"\"\n\t\t\t\t\t\t\t\t\t},\n\t\t\t\t\t\t\t\t\t\"css\": {\n\t\t\t\t\t\t\t\t\t\t\"height\": \"\",\n\t\t\t\t\t\t\t\t\t\t\"color\": \"\",\n\t\t\t\t\t\t\t\t\t\t\"background\": \"\"\n\t\t\t\t\t\t\t\t\t}\n\t\t\t\t\t\t\t\t}\n\t\t\t\t\t\t\t]\n\t\t\t\t\t\t}\n\t\t\t\t\t},\n\t\t\t\t\t\"children\": [\n\t\t\t\t\t\t{\n\t\t\t\t\t\t\t\"id\": 37741,\n\t\t\t\t\t\t\t\"type\": \"panel\",\n\t\t\t\t\t\t\t\"attributes\": {\n\t\t\t\t\t\t\t\t\"name\": {\n\t\t\t\t\t\t\t\t\t\"value\": \"pnlPanel16\"\n\t\t\t\t\t\t\t\t},\n\t\t\t\t\t\t\t\t\"controller\": {\n\t\t\t\t\t\t\t\t\t\"value\": \"\"\n\t\t\t\t\t\t\t\t},\n\t\t\t\t\t\t\t\t\"form\": {\n\t\t\t\t\t\t\t\t\t\"value\": \"\"\n\t\t\t\t\t\t\t\t},\n\t\t\t\t\t\t\t\t\"model\": {\n\t\t\t\t\t\t\t\t\t\"value\": \"moods\"\n\t\t\t\t\t\t\t\t},\n\t\t\t\t\t\t\t\t\"useModel\": {\n\t\t\t\t\t\t\t\t\t\"value\": true\n\t\t\t\t\t\t\t\t},\n\t\t\t\t\t\t\t\t\"collapsible\": {\n\t\t\t\t\t\t\t\t\t\"value\": true\n\t\t\t\t\t\t\t\t},\n\t\t\t\t\t\t\t\t\"classes\": {\n\t\t\t\t\t\t\t\t\t\"value\": \"trans_panel\"\n\t\t\t\t\t\t\t\t},\n\t\t\t\t\t\t\t\t\"display\": {\n\t\t\t\t\t\t\t\t\t\"value\": \"showDetail == true\"\n\t\t\t\t\t\t\t\t},\n\t\t\t\t\t\t\t\t\"title\": {\n\t\t\t\t\t\t\t\t\t\"value\": \"IBM Watson Personality Insights Analysis\"\n\t\t\t\t\t\t\t\t},\n\t\t\t\t\t\t\t\t\"titleVisible\": {\n\t\t\t\t\t\t\t\t\t\"value\": true\n\t\t\t\t\t\t\t\t},\n\t\t\t\t\t\t\t\t\"css\": {\n\t\t\t\t\t\t\t\t\t\"width\": \"100%\",\n\t\t\t\t\t\t\t\t\t\"height\": \"\",\n\t\t\t\t\t\t\t\t\t\"color\": \"#f5deb3\",\n\t\t\t\t\t\t\t\t\t\"background\": \"\",\n\t\t\t\t\t\t\t\t\t\"padding\": \"\",\n\t\t\t\t\t\t\t\t\t\"margin\": \"\",\n\t\t\t\t\t\t\t\t\t\"text-align\": \"\"\n\t\t\t\t\t\t\t\t},\n\t\t\t\t\t\t\t\t\"bodyCss\": {\n\t\t\t\t\t\t\t\t\t\"width\": \"\",\n\t\t\t\t\t\t\t\t\t\"height\": \"\",\n\t\t\t\t\t\t\t\t\t\"color\": \"\",\n\t\t\t\t\t\t\t\t\t\"background\": \"\",\n\t\t\t\t\t\t\t\t\t\"padding\": \"0px\",\n\t\t\t\t\t\t\t\t\t\"margin\": \"\",\n\t\t\t\t\t\t\t\t\t\"text-align\": \"\"\n\t\t\t\t\t\t\t\t},\n\t\t\t\t\t\t\t\t\"bodyClasses\": {\n\t\t\t\t\t\t\t\t\t\"value\": \"floating col-md-4\"\n\t\t\t\t\t\t\t\t},\n\t\t\t\t\t\t\t\t\"bodyDynamicClasses\": {\n\t\t\t\t\t\t\t\t\t\"value\": \"\"\n\t\t\t\t\t\t\t\t},\n\t\t\t\t\t\t\t\t\"style\": {\n\t\t\t\t\t\t\t\t\t\"value\": \"\"\n\t\t\t\t\t\t\t\t},\n\t\t\t\t\t\t\t\t\"layout\": {\n\t\t\t\t\t\t\t\t\t\"rows\": [\n\t\t\t\t\t\t\t\t\t\t{\n\t\t\t\t\t\t\t\t\t\t\t\"cols\": [\n\t\t\t\t\t\t\t\t\t\t\t\t{\n\t\t\t\t\t\t\t\t\t\t\t\t\t\"width\": {\n\t\t\t\t\t\t\t\t\t\t\t\t\t\t\"value\": \"12\"\n\t\t\t\t\t\t\t\t\t\t\t\t\t},\n\t\t\t\t\t\t\t\t\t\t\t\t\t\"classes\": {\n\t\t\t\t\t\t\t\t\t\t\t\t\t\t\"value\": \"\"\n\t\t\t\t\t\t\t\t\t\t\t\t\t},\n\t\t\t\t\t\t\t\t\t\t\t\t\t\"dynamicClasses\": {\n\t\t\t\t\t\t\t\t\t\t\t\t\t\t\"value\": \"\"\n\t\t\t\t\t\t\t\t\t\t\t\t\t},\n\t\t\t\t\t\t\t\t\t\t\t\t\t\"style\": {\n\t\t\t\t\t\t\t\t\t\t\t\t\t\t\"value\": \"\"\n\t\t\t\t\t\t\t\t\t\t\t\t\t},\n\t\t\t\t\t\t\t\t\t\t\t\t\t\"orientation\": {\n\t\t\t\t\t\t\t\t\t\t\t\t\t\t\"value\": \"vertical\"\n\t\t\t\t\t\t\t\t\t\t\t\t\t},\n\t\t\t\t\t\t\t\t\t\t\t\t\t\"alignment\": {\n\t\t\t\t\t\t\t\t\t\t\t\t\t\t\"value\": \"start\"\n\t\t\t\t\t\t\t\t\t\t\t\t\t},\n\t\t\t\t\t\t\t\t\t\t\t\t\t\"disposition\": {\n\t\t\t\t\t\t\t\t\t\t\t\t\t\t\"value\": \"start\"\n\t\t\t\t\t\t\t\t\t\t\t\t\t},\n\t\t\t\t\t\t\t\t\t\t\t\t\t\"css\": {\n\t\t\t\t\t\t\t\t\t\t\t\t\t\t\"color\": \"\",\n\t\t\t\t\t\t\t\t\t\t\t\t\t\t\"background\": \"\",\n\t\t\t\t\t\t\t\t\t\t\t\t\t\t\"padding\": \"0px 0px 0px 10px\",\n\t\t\t\t\t\t\t\t\t\t\t\t\t\t\"text-align\": \"\"\n\t\t\t\t\t\t\t\t\t\t\t\t\t}\n\t\t\t\t\t\t\t\t\t\t\t\t}\n\t\t\t\t\t\t\t\t\t\t\t],\n\t\t\t\t\t\t\t\t\t\t\t\"classes\": {\n\t\t\t\t\t\t\t\t\t\t\t\t\"value\": \"\"\n\t\t\t\t\t\t\t\t\t\t\t},\n\t\t\t\t\t\t\t\t\t\t\t\"dynamicClasses\": {\n\t\t\t\t\t\t\t\t\t\t\t\t\"value\": \"\"\n\t\t\t\t\t\t\t\t\t\t\t},\n\t\t\t\t\t\t\t\t\t\t\t\"style\": {\n\t\t\t\t\t\t\t\t\t\t\t\t\"value\": \"\"\n\t\t\t\t\t\t\t\t\t\t\t},\n\t\t\t\t\t\t\t\t\t\t\t\"css\": {\n\t\t\t\t\t\t\t\t\t\t\t\t\"height\": \"\",\n\t\t\t\t\t\t\t\t\t\t\t\t\"color\": \"\",\n\t\t\t\t\t\t\t\t\t\t\t\t\"background\": \"\"\n\t\t\t\t\t\t\t\t\t\t\t}\n\t\t\t\t\t\t\t\t\t\t}\n\t\t\t\t\t\t\t\t\t]\n\t\t\t\t\t\t\t\t}\n\t\t\t\t\t\t\t},\n\t\t\t\t\t\t\t\"children\": [\n\t\t\t\t\t\t\t\t{\n\t\t\t\t\t\t\t\t\t\"id\": 83273,\n\t\t\t\t\t\t\t\t\t\"type\": \"statictext\",\n\t\t\t\t\t\t\t\t\t\"attributes\": {\n\t\t\t\t\t\t\t\t\t\t\"name\": {\n\t\t\t\t\t\t\t\t\t\t\t\"value\": \"txtText19\"\n\t\t\t\t\t\t\t\t\t\t},\n\t\t\t\t\t\t\t\t\t\t\"bind\": {\n\t\t\t\t\t\t\t\t\t\t\t\"value\": \"\"\n\t\t\t\t\t\t\t\t\t\t},\n\t\t\t\t\t\t\t\t\t\t\"text\": {\n\t\t\t\t\t\t\t\t\t\t\t\"value\": \"{{item.id}}/{{item.name}}\"\n\t\t\t\t\t\t\t\t\t\t},\n\t\t\t\t\t\t\t\t\t\t\"display\": {\n\t\t\t\t\t\t\t\t\t\t\t\"value\": \"true\"\n\t\t\t\t\t\t\t\t\t\t},\n\t\t\t\t\t\t\t\t\t\t\"tooltip\": {\n\t\t\t\t\t\t\t\t\t\t\t\"value\": \"\"\n\t\t\t\t\t\t\t\t\t\t},\n\t\t\t\t\t\t\t\t\t\t\"tooltipPosition\": {\n\t\t\t\t\t\t\t\t\t\t\t\"value\": \"top\"\n\t\t\t\t\t\t\t\t\t\t},\n\t\t\t\t\t\t\t\t\t\t\"counter\": {\n\t\t\t\t\t\t\t\t\t\t\t\"bind\": {\n\t\t\t\t\t\t\t\t\t\t\t\t\"value\": \"\"\n\t\t\t\t\t\t\t\t\t\t\t},\n\t\t\t\t\t\t\t\t\t\t\t\"onclick\": {\n\t\t\t\t\t\t\t\t\t\t\t\t\"value\": \"\"\n\t\t\t\t\t\t\t\t\t\t\t},\n\t\t\t\t\t\t\t\t\t\t\t\"position\": {\n\t\t\t\t\t\t\t\t\t\t\t\t\"value\": \"left\"\n\t\t\t\t\t\t\t\t\t\t\t}\n\t\t\t\t\t\t\t\t\t\t},\n\t\t\t\t\t\t\t\t\t\t\"onclick\": {\n\t\t\t\t\t\t\t\t\t\t\t\"value\": \"\"\n\t\t\t\t\t\t\t\t\t\t},\n\t\t\t\t\t\t\t\t\t\t\"classes\": {\n\t\t\t\t\t\t\t\t\t\t\t\"value\": \"h5\"\n\t\t\t\t\t\t\t\t\t\t},\n\t\t\t\t\t\t\t\t\t\t\"dynamicClasses\": {\n\t\t\t\t\t\t\t\t\t\t\t\"value\": \"\"\n\t\t\t\t\t\t\t\t\t\t},\n\t\t\t\t\t\t\t\t\t\t\"style\": {\n\t\t\t\t\t\t\t\t\t\t\t\"value\": \"\"\n\t\t\t\t\t\t\t\t\t\t},\n\t\t\t\t\t\t\t\t\t\t\"css\": {\n\t\t\t\t\t\t\t\t\t\t\t\"width\": \"\",\n\t\t\t\t\t\t\t\t\t\t\t\"height\": \"\",\n\t\t\t\t\t\t\t\t\t\t\t\"color\": \"#ffffff\",\n\t\t\t\t\t\t\t\t\t\t\t\"background\": \"\",\n\t\t\t\t\t\t\t\t\t\t\t\"padding\": \"\",\n\t\t\t\t\t\t\t\t\t\t\t\"margin\": \"\",\n\t\t\t\t\t\t\t\t\t\t\t\"text-align\": \"\"\n\t\t\t\t\t\t\t\t\t\t},\n\t\t\t\t\t\t\t\t\t\t\"containerClasses\": {\n\t\t\t\t\t\t\t\t\t\t\t\"value\": \"\"\n\t\t\t\t\t\t\t\t\t\t},\n\t\t\t\t\t\t\t\t\t\t\"containerDynamicClasses\": {\n\t\t\t\t\t\t\t\t\t\t\t\"value\": \"\"\n\t\t\t\t\t\t\t\t\t\t},\n\t\t\t\t\t\t\t\t\t\t\"containerStyle\": {\n\t\t\t\t\t\t\t\t\t\t\t\"value\": \"\"\n\t\t\t\t\t\t\t\t\t\t},\n\t\t\t\t\t\t\t\t\t\t\"containerCss\": {\n\t\t\t\t\t\t\t\t\t\t\t\"width\": \"\",\n\t\t\t\t\t\t\t\t\t\t\t\"height\": \"\",\n\t\t\t\t\t\t\t\t\t\t\t\"color\": \"\",\n\t\t\t\t\t\t\t\t\t\t\t\"background\": \"\",\n\t\t\t\t\t\t\t\t\t\t\t\"padding\": \"\",\n\t\t\t\t\t\t\t\t\t\t\t\"margin\": \"\",\n\t\t\t\t\t\t\t\t\t\t\t\"text-align\": \"\"\n\t\t\t\t\t\t\t\t\t\t}\n\t\t\t\t\t\t\t\t\t},\n\t\t\t\t\t\t\t\t\t\"children\": [],\n\t\t\t\t\t\t\t\t\t\"container\": \"layout_0_row_0_column_0\"\n\t\t\t\t\t\t\t\t},\n\t\t\t\t\t\t\t\t{\n\t\t\t\t\t\t\t\t\t\"id\": 43161,\n\t\t\t\t\t\t\t\t\t\"type\": \"panel\",\n\t\t\t\t\t\t\t\t\t\"attributes\": {\n\t\t\t\t\t\t\t\t\t\t\"name\": {\n\t\t\t\t\t\t\t\t\t\t\t\"value\": \"pnlPanel18\"\n\t\t\t\t\t\t\t\t\t\t},\n\t\t\t\t\t\t\t\t\t\t\"controller\": {\n\t\t\t\t\t\t\t\t\t\t\t\"value\": \"\"\n\t\t\t\t\t\t\t\t\t\t},\n\t\t\t\t\t\t\t\t\t\t\"form\": {\n\t\t\t\t\t\t\t\t\t\t\t\"value\": \"\"\n\t\t\t\t\t\t\t\t\t\t},\n\t\t\t\t\t\t\t\t\t\t\"model\": {\n\t\t\t\t\t\t\t\t\t\t\t\"value\": \"item.children\"\n\t\t\t\t\t\t\t\t\t\t},\n\t\t\t\t\t\t\t\t\t\t\"useModel\": {\n\t\t\t\t\t\t\t\t\t\t\t\"value\": true\n\t\t\t\t\t\t\t\t\t\t},\n\t\t\t\t\t\t\t\t\t\t\"collapsible\": {\n\t\t\t\t\t\t\t\t\t\t\t\"value\": false\n\t\t\t\t\t\t\t\t\t\t},\n\t\t\t\t\t\t\t\t\t\t\"classes\": {\n\t\t\t\t\t\t\t\t\t\t\t\"value\": \"trans_panel\"\n\t\t\t\t\t\t\t\t\t\t},\n\t\t\t\t\t\t\t\t\t\t\"display\": {\n\t\t\t\t\t\t\t\t\t\t\t\"value\": \"\"\n\t\t\t\t\t\t\t\t\t\t},\n\t\t\t\t\t\t\t\t\t\t\"title\": {\n\t\t\t\t\t\t\t\t\t\t\t\"value\": \"\"\n\t\t\t\t\t\t\t\t\t\t},\n\t\t\t\t\t\t\t\t\t\t\"titleVisible\": {\n\t\t\t\t\t\t\t\t\t\t\t\"value\": false\n\t\t\t\t\t\t\t\t\t\t},\n\t\t\t\t\t\t\t\t\t\t\"css\": {\n\t\t\t\t\t\t\t\t\t\t\t\"width\": \"100%\",\n\t\t\t\t\t\t\t\t\t\t\t\"height\": \"\",\n\t\t\t\t\t\t\t\t\t\t\t\"color\": \"\",\n\t\t\t\t\t\t\t\t\t\t\t\"background\": \"\",\n\t\t\t\t\t\t\t\t\t\t\t\"padding\": \"\",\n\t\t\t\t\t\t\t\t\t\t\t\"margin\": \"\",\n\t\t\t\t\t\t\t\t\t\t\t\"text-align\": \"\"\n\t\t\t\t\t\t\t\t\t\t},\n\t\t\t\t\t\t\t\t\t\t\"bodyCss\": {\n\t\t\t\t\t\t\t\t\t\t\t\"width\": \"\",\n\t\t\t\t\t\t\t\t\t\t\t\"height\": \"\",\n\t\t\t\t\t\t\t\t\t\t\t\"color\": \"\",\n\t\t\t\t\t\t\t\t\t\t\t\"background\": \"\",\n\t\t\t\t\t\t\t\t\t\t\t\"padding\": \"\",\n\t\t\t\t\t\t\t\t\t\t\t\"margin\": \"\",\n\t\t\t\t\t\t\t\t\t\t\t\"text-align\": \"\"\n\t\t\t\t\t\t\t\t\t\t},\n\t\t\t\t\t\t\t\t\t\t\"bodyClasses\": {\n\t\t\t\t\t\t\t\t\t\t\t\"value\": \"\"\n\t\t\t\t\t\t\t\t\t\t},\n\t\t\t\t\t\t\t\t\t\t\"bodyDynamicClasses\": {\n\t\t\t\t\t\t\t\t\t\t\t\"value\": \"\"\n\t\t\t\t\t\t\t\t\t\t},\n\t\t\t\t\t\t\t\t\t\t\"style\": {\n\t\t\t\t\t\t\t\t\t\t\t\"value\": \"\"\n\t\t\t\t\t\t\t\t\t\t},\n\t\t\t\t\t\t\t\t\t\t\"layout\": {\n\t\t\t\t\t\t\t\t\t\t\t\"rows\": [\n\t\t\t\t\t\t\t\t\t\t\t\t{\n\t\t\t\t\t\t\t\t\t\t\t\t\t\"cols\": [\n\t\t\t\t\t\t\t\t\t\t\t\t\t\t{\n\t\t\t\t\t\t\t\t\t\t\t\t\t\t\t\"width\": {\n\t\t\t\t\t\t\t\t\t\t\t\t\t\t\t\t\"value\": \"12\"\n\t\t\t\t\t\t\t\t\t\t\t\t\t\t\t},\n\t\t\t\t\t\t\t\t\t\t\t\t\t\t\t\"classes\": {\n\t\t\t\t\t\t\t\t\t\t\t\t\t\t\t\t\"value\": \"\"\n\t\t\t\t\t\t\t\t\t\t\t\t\t\t\t},\n\t\t\t\t\t\t\t\t\t\t\t\t\t\t\t\"dynamicClasses\": {\n\t\t\t\t\t\t\t\t\t\t\t\t\t\t\t\t\"value\": \"\"\n\t\t\t\t\t\t\t\t\t\t\t\t\t\t\t},\n\t\t\t\t\t\t\t\t\t\t\t\t\t\t\t\"style\": {\n\t\t\t\t\t\t\t\t\t\t\t\t\t\t\t\t\"value\": \"\"\n\t\t\t\t\t\t\t\t\t\t\t\t\t\t\t},\n\t\t\t\t\t\t\t\t\t\t\t\t\t\t\t\"orientation\": {\n\t\t\t\t\t\t\t\t\t\t\t\t\t\t\t\t\"value\": \"vertical\"\n\t\t\t\t\t\t\t\t\t\t\t\t\t\t\t},\n\t\t\t\t\t\t\t\t\t\t\t\t\t\t\t\"alignment\": {\n\t\t\t\t\t\t\t\t\t\t\t\t\t\t\t\t\"value\": \"start\"\n\t\t\t\t\t\t\t\t\t\t\t\t\t\t\t},\n\t\t\t\t\t\t\t\t\t\t\t\t\t\t\t\"disposition\": {\n\t\t\t\t\t\t\t\t\t\t\t\t\t\t\t\t\"value\": \"space_around\"\n\t\t\t\t\t\t\t\t\t\t\t\t\t\t\t},\n\t\t\t\t\t\t\t\t\t\t\t\t\t\t\t\"css\": {\n\t\t\t\t\t\t\t\t\t\t\t\t\t\t\t\t\"color\": \"\",\n\t\t\t\t\t\t\t\t\t\t\t\t\t\t\t\t\"background\": \"\",\n\t\t\t\t\t\t\t\t\t\t\t\t\t\t\t\t\"padding\": \"\",\n\t\t\t\t\t\t\t\t\t\t\t\t\t\t\t\t\"text-align\": \"\"\n\t\t\t\t\t\t\t\t\t\t\t\t\t\t\t}\n\t\t\t\t\t\t\t\t\t\t\t\t\t\t}\n\t\t\t\t\t\t\t\t\t\t\t\t\t],\n\t\t\t\t\t\t\t\t\t\t\t\t\t\"classes\": {\n\t\t\t\t\t\t\t\t\t\t\t\t\t\t\"value\": \"\"\n\t\t\t\t\t\t\t\t\t\t\t\t\t},\n\t\t\t\t\t\t\t\t\t\t\t\t\t\"dynamicClasses\": {\n\t\t\t\t\t\t\t\t\t\t\t\t\t\t\"value\": \"\"\n\t\t\t\t\t\t\t\t\t\t\t\t\t},\n\t\t\t\t\t\t\t\t\t\t\t\t\t\"style\": {\n\t\t\t\t\t\t\t\t\t\t\t\t\t\t\"value\": \"\"\n\t\t\t\t\t\t\t\t\t\t\t\t\t},\n\t\t\t\t\t\t\t\t\t\t\t\t\t\"css\": {\n\t\t\t\t\t\t\t\t\t\t\t\t\t\t\"height\": \"\",\n\t\t\t\t\t\t\t\t\t\t\t\t\t\t\"color\": \"\",\n\t\t\t\t\t\t\t\t\t\t\t\t\t\t\"background\": \"\"\n\t\t\t\t\t\t\t\t\t\t\t\t\t}\n\t\t\t\t\t\t\t\t\t\t\t\t}\n\t\t\t\t\t\t\t\t\t\t\t]\n\t\t\t\t\t\t\t\t\t\t}\n\t\t\t\t\t\t\t\t\t},\n\t\t\t\t\t\t\t\t\t\"children\": [\n\t\t\t\t\t\t\t\t\t\t{\n\t\t\t\t\t\t\t\t\t\t\t\"id\": 84352,\n\t\t\t\t\t\t\t\t\t\t\t\"type\": \"panel\",\n\t\t\t\t\t\t\t\t\t\t\t\"attributes\": {\n\t\t\t\t\t\t\t\t\t\t\t\t\"name\": {\n\t\t\t\t\t\t\t\t\t\t\t\t\t\"value\": \"pnlPanel17\"\n\t\t\t\t\t\t\t\t\t\t\t\t},\n\t\t\t\t\t\t\t\t\t\t\t\t\"controller\": {\n\t\t\t\t\t\t\t\t\t\t\t\t\t\"value\": \"\"\n\t\t\t\t\t\t\t\t\t\t\t\t},\n\t\t\t\t\t\t\t\t\t\t\t\t\"form\": {\n\t\t\t\t\t\t\t\t\t\t\t\t\t\"value\": \"\"\n\t\t\t\t\t\t\t\t\t\t\t\t},\n\t\t\t\t\t\t\t\t\t\t\t\t\"model\": {\n\t\t\t\t\t\t\t\t\t\t\t\t\t\"value\": \"item.children\"\n\t\t\t\t\t\t\t\t\t\t\t\t},\n\t\t\t\t\t\t\t\t\t\t\t\t\"useModel\": {\n\t\t\t\t\t\t\t\t\t\t\t\t\t\"value\": true\n\t\t\t\t\t\t\t\t\t\t\t\t},\n\t\t\t\t\t\t\t\t\t\t\t\t\"collapsible\": {\n\t\t\t\t\t\t\t\t\t\t\t\t\t\"value\": false\n\t\t\t\t\t\t\t\t\t\t\t\t},\n\t\t\t\t\t\t\t\t\t\t\t\t\"classes\": {\n\t\t\t\t\t\t\t\t\t\t\t\t\t\"value\": \"trans_panel\"\n\t\t\t\t\t\t\t\t\t\t\t\t},\n\t\t\t\t\t\t\t\t\t\t\t\t\"display\": {\n\t\t\t\t\t\t\t\t\t\t\t\t\t\"value\": \"\"\n\t\t\t\t\t\t\t\t\t\t\t\t},\n\t\t\t\t\t\t\t\t\t\t\t\t\"title\": {\n\t\t\t\t\t\t\t\t\t\t\t\t\t\"value\": \"\"\n\t\t\t\t\t\t\t\t\t\t\t\t},\n\t\t\t\t\t\t\t\t\t\t\t\t\"titleVisible\": {\n\t\t\t\t\t\t\t\t\t\t\t\t\t\"value\": false\n\t\t\t\t\t\t\t\t\t\t\t\t},\n\t\t\t\t\t\t\t\t\t\t\t\t\"css\": {\n\t\t\t\t\t\t\t\t\t\t\t\t\t\"width\": \"100%\",\n\t\t\t\t\t\t\t\t\t\t\t\t\t\"height\": \"\",\n\t\t\t\t\t\t\t\t\t\t\t\t\t\"color\": \"\",\n\t\t\t\t\t\t\t\t\t\t\t\t\t\"background\": \"\",\n\t\t\t\t\t\t\t\t\t\t\t\t\t\"padding\": \"\",\n\t\t\t\t\t\t\t\t\t\t\t\t\t\"margin\": \"\",\n\t\t\t\t\t\t\t\t\t\t\t\t\t\"text-align\": \"\"\n\t\t\t\t\t\t\t\t\t\t\t\t},\n\t\t\t\t\t\t\t\t\t\t\t\t\"bodyCss\": {\n\t\t\t\t\t\t\t\t\t\t\t\t\t\"width\": \"\",\n\t\t\t\t\t\t\t\t\t\t\t\t\t\"height\": \"\",\n\t\t\t\t\t\t\t\t\t\t\t\t\t\"color\": \"\",\n\t\t\t\t\t\t\t\t\t\t\t\t\t\"background\": \"\",\n\t\t\t\t\t\t\t\t\t\t\t\t\t\"padding\": \"0px\",\n\t\t\t\t\t\t\t\t\t\t\t\t\t\"margin\": \"\",\n\t\t\t\t\t\t\t\t\t\t\t\t\t\"text-align\": \"\"\n\t\t\t\t\t\t\t\t\t\t\t\t},\n\t\t\t\t\t\t\t\t\t\t\t\t\"bodyClasses\": {\n\t\t\t\t\t\t\t\t\t\t\t\t\t\"value\": \"\"\n\t\t\t\t\t\t\t\t\t\t\t\t},\n\t\t\t\t\t\t\t\t\t\t\t\t\"bodyDynamicClasses\": {\n\t\t\t\t\t\t\t\t\t\t\t\t\t\"value\": \"\"\n\t\t\t\t\t\t\t\t\t\t\t\t},\n\t\t\t\t\t\t\t\t\t\t\t\t\"style\": {\n\t\t\t\t\t\t\t\t\t\t\t\t\t\"value\": \"\"\n\t\t\t\t\t\t\t\t\t\t\t\t},\n\t\t\t\t\t\t\t\t\t\t\t\t\"layout\": {\n\t\t\t\t\t\t\t\t\t\t\t\t\t\"rows\": [\n\t\t\t\t\t\t\t\t\t\t\t\t\t\t{\n\t\t\t\t\t\t\t\t\t\t\t\t\t\t\t\"cols\": [\n\t\t\t\t\t\t\t\t\t\t\t\t\t\t\t\t{\n\t\t\t\t\t\t\t\t\t\t\t\t\t\t\t\t\t\"width\": {\n\t\t\t\t\t\t\t\t\t\t\t\t\t\t\t\t\t\t\"value\": \"12\"\n\t\t\t\t\t\t\t\t\t\t\t\t\t\t\t\t\t},\n\t\t\t\t\t\t\t\t\t\t\t\t\t\t\t\t\t\"orientation\": {\n\t\t\t\t\t\t\t\t\t\t\t\t\t\t\t\t\t\t\"value\": \"vertical\"\n\t\t\t\t\t\t\t\t\t\t\t\t\t\t\t\t\t},\n\t\t\t\t\t\t\t\t\t\t\t\t\t\t\t\t\t\"alignment\": {\n\t\t\t\t\t\t\t\t\t\t\t\t\t\t\t\t\t\t\"value\": \"start\"\n\t\t\t\t\t\t\t\t\t\t\t\t\t\t\t\t\t},\n\t\t\t\t\t\t\t\t\t\t\t\t\t\t\t\t\t\"disposition\": {\n\t\t\t\t\t\t\t\t\t\t\t\t\t\t\t\t\t\t\"value\": \"space_around\"\n\t\t\t\t\t\t\t\t\t\t\t\t\t\t\t\t\t},\n\t\t\t\t\t\t\t\t\t\t\t\t\t\t\t\t\t\"classes\": {\n\t\t\t\t\t\t\t\t\t\t\t\t\t\t\t\t\t\t\"value\": \"\"\n\t\t\t\t\t\t\t\t\t\t\t\t\t\t\t\t\t},\n\t\t\t\t\t\t\t\t\t\t\t\t\t\t\t\t\t\"dynamicClasses\": {\n\t\t\t\t\t\t\t\t\t\t\t\t\t\t\t\t\t\t\"value\": \"\"\n\t\t\t\t\t\t\t\t\t\t\t\t\t\t\t\t\t},\n\t\t\t\t\t\t\t\t\t\t\t\t\t\t\t\t\t\"style\": {\n\t\t\t\t\t\t\t\t\t\t\t\t\t\t\t\t\t\t\"value\": \"\"\n\t\t\t\t\t\t\t\t\t\t\t\t\t\t\t\t\t},\n\t\t\t\t\t\t\t\t\t\t\t\t\t\t\t\t\t\"css\": {\n\t\t\t\t\t\t\t\t\t\t\t\t\t\t\t\t\t\t\"color\": \"\",\n\t\t\t\t\t\t\t\t\t\t\t\t\t\t\t\t\t\t\"background\": \"\",\n\t\t\t\t\t\t\t\t\t\t\t\t\t\t\t\t\t\t\"padding\": \"\",\n\t\t\t\t\t\t\t\t\t\t\t\t\t\t\t\t\t\t\"text-align\": \"\"\n\t\t\t\t\t\t\t\t\t\t\t\t\t\t\t\t\t}\n\t\t\t\t\t\t\t\t\t\t\t\t\t\t\t\t}\n\t\t\t\t\t\t\t\t\t\t\t\t\t\t\t],\n\t\t\t\t\t\t\t\t\t\t\t\t\t\t\t\"classes\": {\n\t\t\t\t\t\t\t\t\t\t\t\t\t\t\t\t\"value\": \"\"\n\t\t\t\t\t\t\t\t\t\t\t\t\t\t\t},\n\t\t\t\t\t\t\t\t\t\t\t\t\t\t\t\"dynamicClasses\": {\n\t\t\t\t\t\t\t\t\t\t\t\t\t\t\t\t\"value\": \"\"\n\t\t\t\t\t\t\t\t\t\t\t\t\t\t\t},\n\t\t\t\t\t\t\t\t\t\t\t\t\t\t\t\"style\": {\n\t\t\t\t\t\t\t\t\t\t\t\t\t\t\t\t\"value\": \"\"\n\t\t\t\t\t\t\t\t\t\t\t\t\t\t\t},\n\t\t\t\t\t\t\t\t\t\t\t\t\t\t\t\"css\": {\n\t\t\t\t\t\t\t\t\t\t\t\t\t\t\t\t\"height\": \"\",\n\t\t\t\t\t\t\t\t\t\t\t\t\t\t\t\t\"color\": \"\",\n\t\t\t\t\t\t\t\t\t\t\t\t\t\t\t\t\"background\": \"\"\n\t\t\t\t\t\t\t\t\t\t\t\t\t\t\t}\n\t\t\t\t\t\t\t\t\t\t\t\t\t\t}\n\t\t\t\t\t\t\t\t\t\t\t\t\t]\n\t\t\t\t\t\t\t\t\t\t\t\t}\n\t\t\t\t\t\t\t\t\t\t\t},\n\t\t\t\t\t\t\t\t\t\t\t\"children\": [\n\t\t\t\t\t\t\t\t\t\t\t\t{\n\t\t\t\t\t\t\t\t\t\t\t\t\t\"id\": 10865,\n\t\t\t\t\t\t\t\t\t\t\t\t\t\"type\": \"rating\",\n\t\t\t\t\t\t\t\t\t\t\t\t\t\"attributes\": {\n\t\t\t\t\t\t\t\t\t\t\t\t\t\t\"name\": {\n\t\t\t\t\t\t\t\t\t\t\t\t\t\t\t\"value\": \"rtRating4\"\n\t\t\t\t\t\t\t\t\t\t\t\t\t\t},\n\t\t\t\t\t\t\t\t\t\t\t\t\t\t\"label\": {\n\t\t\t\t\t\t\t\t\t\t\t\t\t\t\t\"value\": \"Label\"\n\t\t\t\t\t\t\t\t\t\t\t\t\t\t},\n\t\t\t\t\t\t\t\t\t\t\t\t\t\t\"labelVisible\": {\n\t\t\t\t\t\t\t\t\t\t\t\t\t\t\t\"value\": \"no\"\n\t\t\t\t\t\t\t\t\t\t\t\t\t\t},\n\t\t\t\t\t\t\t\t\t\t\t\t\t\t\"labelPosition\": {\n\t\t\t\t\t\t\t\t\t\t\t\t\t\t\t\"value\": \"center\"\n\t\t\t\t\t\t\t\t\t\t\t\t\t\t},\n\t\t\t\t\t\t\t\t\t\t\t\t\t\t\"tooltip\": {\n\t\t\t\t\t\t\t\t\t\t\t\t\t\t\t\"value\": \"\"\n\t\t\t\t\t\t\t\t\t\t\t\t\t\t},\n\t\t\t\t\t\t\t\t\t\t\t\t\t\t\"tooltipPosition\": {\n\t\t\t\t\t\t\t\t\t\t\t\t\t\t\t\"value\": \"top\"\n\t\t\t\t\t\t\t\t\t\t\t\t\t\t},\n\t\t\t\t\t\t\t\t\t\t\t\t\t\t\"min\": {\n\t\t\t\t\t\t\t\t\t\t\t\t\t\t\t\"value\": \"0\"\n\t\t\t\t\t\t\t\t\t\t\t\t\t\t},\n\t\t\t\t\t\t\t\t\t\t\t\t\t\t\"max\": {\n\t\t\t\t\t\t\t\t\t\t\t\t\t\t\t\"value\": \"1\"\n\t\t\t\t\t\t\t\t\t\t\t\t\t\t},\n\t\t\t\t\t\t\t\t\t\t\t\t\t\t\"step\": {\n\t\t\t\t\t\t\t\t\t\t\t\t\t\t\t\"value\": \"0.01\"\n\t\t\t\t\t\t\t\t\t\t\t\t\t\t},\n\t\t\t\t\t\t\t\t\t\t\t\t\t\t\"symbol\": {\n\t\t\t\t\t\t\t\t\t\t\t\t\t\t\t\"name\": \"star\",\n\t\t\t\t\t\t\t\t\t\t\t\t\t\t\t\"value\": \"&#57350;\"\n\t\t\t\t\t\t\t\t\t\t\t\t\t\t},\n\t\t\t\t\t\t\t\t\t\t\t\t\t\t\"symbolsNumber\": {\n\t\t\t\t\t\t\t\t\t\t\t\t\t\t\t\"value\": \"5\"\n\t\t\t\t\t\t\t\t\t\t\t\t\t\t},\n\t\t\t\t\t\t\t\t\t\t\t\t\t\t\"caption\": {\n\t\t\t\t\t\t\t\t\t\t\t\t\t\t\t\"value\": \"{{item.name}} ({{item.percentage}})\"\n\t\t\t\t\t\t\t\t\t\t\t\t\t\t},\n\t\t\t\t\t\t\t\t\t\t\t\t\t\t\"captionVisible\": {\n\t\t\t\t\t\t\t\t\t\t\t\t\t\t\t\"value\": \"yes\"\n\t\t\t\t\t\t\t\t\t\t\t\t\t\t},\n\t\t\t\t\t\t\t\t\t\t\t\t\t\t\"clearVisible\": {\n\t\t\t\t\t\t\t\t\t\t\t\t\t\t\t\"value\": \"no\"\n\t\t\t\t\t\t\t\t\t\t\t\t\t\t},\n\t\t\t\t\t\t\t\t\t\t\t\t\t\t\"property\": {\n\t\t\t\t\t\t\t\t\t\t\t\t\t\t\t\"value\": \"item.percentage\"\n\t\t\t\t\t\t\t\t\t\t\t\t\t\t},\n\t\t\t\t\t\t\t\t\t\t\t\t\t\t\"propertyInit\": {\n\t\t\t\t\t\t\t\t\t\t\t\t\t\t\t\"value\": \"\"\n\t\t\t\t\t\t\t\t\t\t\t\t\t\t},\n\t\t\t\t\t\t\t\t\t\t\t\t\t\t\"display\": {\n\t\t\t\t\t\t\t\t\t\t\t\t\t\t\t\"value\": \"true\"\n\t\t\t\t\t\t\t\t\t\t\t\t\t\t},\n\t\t\t\t\t\t\t\t\t\t\t\t\t\t\"disabled\": {\n\t\t\t\t\t\t\t\t\t\t\t\t\t\t\t\"value\": \"true\"\n\t\t\t\t\t\t\t\t\t\t\t\t\t\t},\n\t\t\t\t\t\t\t\t\t\t\t\t\t\t\"containerClasses\": {\n\t\t\t\t\t\t\t\t\t\t\t\t\t\t\t\"value\": \"\"\n\t\t\t\t\t\t\t\t\t\t\t\t\t\t},\n\t\t\t\t\t\t\t\t\t\t\t\t\t\t\"containerDynamicClasses\": {\n\t\t\t\t\t\t\t\t\t\t\t\t\t\t\t\"value\": \"\"\n\t\t\t\t\t\t\t\t\t\t\t\t\t\t},\n\t\t\t\t\t\t\t\t\t\t\t\t\t\t\"containerCss\": {\n\t\t\t\t\t\t\t\t\t\t\t\t\t\t\t\"width\": \"\",\n\t\t\t\t\t\t\t\t\t\t\t\t\t\t\t\"height\": \"\",\n\t\t\t\t\t\t\t\t\t\t\t\t\t\t\t\"color\": \"\",\n\t\t\t\t\t\t\t\t\t\t\t\t\t\t\t\"background\": \"\",\n\t\t\t\t\t\t\t\t\t\t\t\t\t\t\t\"padding\": \"\",\n\t\t\t\t\t\t\t\t\t\t\t\t\t\t\t\"margin\": \"5px 0px 0px 0px\",\n\t\t\t\t\t\t\t\t\t\t\t\t\t\t\t\"text-align\": \"\"\n\t\t\t\t\t\t\t\t\t\t\t\t\t\t},\n\t\t\t\t\t\t\t\t\t\t\t\t\t\t\"containerStyle\": {\n\t\t\t\t\t\t\t\t\t\t\t\t\t\t\t\"value\": \"\"\n\t\t\t\t\t\t\t\t\t\t\t\t\t\t},\n\t\t\t\t\t\t\t\t\t\t\t\t\t\t\"classes\": {\n\t\t\t\t\t\t\t\t\t\t\t\t\t\t\t\"value\": \"\"\n\t\t\t\t\t\t\t\t\t\t\t\t\t\t},\n\t\t\t\t\t\t\t\t\t\t\t\t\t\t\"dynamicClasses\": {\n\t\t\t\t\t\t\t\t\t\t\t\t\t\t\t\"value\": \"\"\n\t\t\t\t\t\t\t\t\t\t\t\t\t\t},\n\t\t\t\t\t\t\t\t\t\t\t\t\t\t\"css\": {\n\t\t\t\t\t\t\t\t\t\t\t\t\t\t\t\"size\": \"sm\",\n\t\t\t\t\t\t\t\t\t\t\t\t\t\t\t\"color\": \"#4682b4\",\n\t\t\t\t\t\t\t\t\t\t\t\t\t\t\t\"background\": \"#e3e3e3\"\n\t\t\t\t\t\t\t\t\t\t\t\t\t\t},\n\t\t\t\t\t\t\t\t\t\t\t\t\t\t\"style\": {\n\t\t\t\t\t\t\t\t\t\t\t\t\t\t\t\"value\": \"\"\n\t\t\t\t\t\t\t\t\t\t\t\t\t\t},\n\t\t\t\t\t\t\t\t\t\t\t\t\t\t\"onchange\": {\n\t\t\t\t\t\t\t\t\t\t\t\t\t\t\t\"value\": \"\"\n\t\t\t\t\t\t\t\t\t\t\t\t\t\t}\n\t\t\t\t\t\t\t\t\t\t\t\t\t},\n\t\t\t\t\t\t\t\t\t\t\t\t\t\"children\": [],\n\t\t\t\t\t\t\t\t\t\t\t\t\t\"container\": \"layout_0_row_0_column_0\"\n\t\t\t\t\t\t\t\t\t\t\t\t}\n\t\t\t\t\t\t\t\t\t\t\t],\n\t\t\t\t\t\t\t\t\t\t\t\"container\": \"layout_0_row_0_column_0\"\n\t\t\t\t\t\t\t\t\t\t}\n\t\t\t\t\t\t\t\t\t],\n\t\t\t\t\t\t\t\t\t\"container\": \"layout_0_row_0_column_0\"\n\t\t\t\t\t\t\t\t}\n\t\t\t\t\t\t\t],\n\t\t\t\t\t\t\t\"container\": \"layout_0_row_3_column_0\"\n\t\t\t\t\t\t},\n\t\t\t\t\t\t{\n\t\t\t\t\t\t\t\"id\": 73818,\n\t\t\t\t\t\t\t\"type\": \"statictext\",\n\t\t\t\t\t\t\t\"attributes\": {\n\t\t\t\t\t\t\t\t\"name\": {\n\t\t\t\t\t\t\t\t\t\"value\": \"txtText9\"\n\t\t\t\t\t\t\t\t},\n\t\t\t\t\t\t\t\t\"bind\": {\n\t\t\t\t\t\t\t\t\t\"value\": \"\"\n\t\t\t\t\t\t\t\t},\n\t\t\t\t\t\t\t\t\"text\": {\n\t\t\t\t\t\t\t\t\t\"value\": \"\"\n\t\t\t\t\t\t\t\t},\n\t\t\t\t\t\t\t\t\"display\": {\n\t\t\t\t\t\t\t\t\t\"value\": \"true\"\n\t\t\t\t\t\t\t\t},\n\t\t\t\t\t\t\t\t\"tooltip\": {\n\t\t\t\t\t\t\t\t\t\"value\": \"\"\n\t\t\t\t\t\t\t\t},\n\t\t\t\t\t\t\t\t\"tooltipPosition\": {\n\t\t\t\t\t\t\t\t\t\"value\": \"top\"\n\t\t\t\t\t\t\t\t},\n\t\t\t\t\t\t\t\t\"counter\": {\n\t\t\t\t\t\t\t\t\t\"bind\": {\n\t\t\t\t\t\t\t\t\t\t\"value\": \"\"\n\t\t\t\t\t\t\t\t\t},\n\t\t\t\t\t\t\t\t\t\"onclick\": {\n\t\t\t\t\t\t\t\t\t\t\"value\": \"\"\n\t\t\t\t\t\t\t\t\t},\n\t\t\t\t\t\t\t\t\t\"position\": {\n\t\t\t\t\t\t\t\t\t\t\"value\": \"left\"\n\t\t\t\t\t\t\t\t\t}\n\t\t\t\t\t\t\t\t},\n\t\t\t\t\t\t\t\t\"onclick\": {\n\t\t\t\t\t\t\t\t\t\"value\": \"navigate(-1)\"\n\t\t\t\t\t\t\t\t},\n\t\t\t\t\t\t\t\t\"classes\": {\n\t\t\t\t\t\t\t\t\t\"value\": \"boxStyle fa fa-chevron-left fa-2x\"\n\t\t\t\t\t\t\t\t},\n\t\t\t\t\t\t\t\t\"dynamicClasses\": {\n\t\t\t\t\t\t\t\t\t\"value\": \"\"\n\t\t\t\t\t\t\t\t},\n\t\t\t\t\t\t\t\t\"style\": {\n\t\t\t\t\t\t\t\t\t\"value\": \"\"\n\t\t\t\t\t\t\t\t},\n\t\t\t\t\t\t\t\t\"css\": {\n\t\t\t\t\t\t\t\t\t\"width\": \"100%\",\n\t\t\t\t\t\t\t\t\t\"height\": \"\",\n\t\t\t\t\t\t\t\t\t\"color\": \"\",\n\t\t\t\t\t\t\t\t\t\"background\": \"#e9967a\",\n\t\t\t\t\t\t\t\t\t\"padding\": \"10px\",\n\t\t\t\t\t\t\t\t\t\"margin\": \"\",\n\t\t\t\t\t\t\t\t\t\"text-align\": \"center\"\n\t\t\t\t\t\t\t\t},\n\t\t\t\t\t\t\t\t\"containerClasses\": {\n\t\t\t\t\t\t\t\t\t\"value\": \"\"\n\t\t\t\t\t\t\t\t},\n\t\t\t\t\t\t\t\t\"containerDynamicClasses\": {\n\t\t\t\t\t\t\t\t\t\"value\": \"\"\n\t\t\t\t\t\t\t\t},\n\t\t\t\t\t\t\t\t\"containerStyle\": {\n\t\t\t\t\t\t\t\t\t\"value\": \"\"\n\t\t\t\t\t\t\t\t},\n\t\t\t\t\t\t\t\t\"containerCss\": {\n\t\t\t\t\t\t\t\t\t\"width\": \"120px\",\n\t\t\t\t\t\t\t\t\t\"height\": \"\",\n\t\t\t\t\t\t\t\t\t\"color\": \"\",\n\t\t\t\t\t\t\t\t\t\"background\": \"\",\n\t\t\t\t\t\t\t\t\t\"padding\": \"\",\n\t\t\t\t\t\t\t\t\t\"margin\": \"10px 0px 10px 0px\",\n\t\t\t\t\t\t\t\t\t\"text-align\": \"\"\n\t\t\t\t\t\t\t\t}\n\t\t\t\t\t\t\t},\n\t\t\t\t\t\t\t\"children\": [],\n\t\t\t\t\t\t\t\"container\": \"layout_0_row_0_column_0\"\n\t\t\t\t\t\t},\n\t\t\t\t\t\t{\n\t\t\t\t\t\t\t\"id\": 18356,\n\t\t\t\t\t\t\t\"type\": \"inputfield\",\n\t\t\t\t\t\t\t\"attributes\": {\n\t\t\t\t\t\t\t\t\"name\": {\n\t\t\t\t\t\t\t\t\t\"value\": \"fldInput1\"\n\t\t\t\t\t\t\t\t},\n\t\t\t\t\t\t\t\t\"type\": {\n\t\t\t\t\t\t\t\t\t\"value\": \"text\"\n\t\t\t\t\t\t\t\t},\n\t\t\t\t\t\t\t\t\"label\": {\n\t\t\t\t\t\t\t\t\t\"value\": \"Label\"\n\t\t\t\t\t\t\t\t},\n\t\t\t\t\t\t\t\t\"labelVisible\": {\n\t\t\t\t\t\t\t\t\t\"value\": \"no\"\n\t\t\t\t\t\t\t\t},\n\t\t\t\t\t\t\t\t\"tooltip\": {\n\t\t\t\t\t\t\t\t\t\"value\": \"\"\n\t\t\t\t\t\t\t\t},\n\t\t\t\t\t\t\t\t\"tooltipPosition\": {\n\t\t\t\t\t\t\t\t\t\"value\": \"top\"\n\t\t\t\t\t\t\t\t},\n\t\t\t\t\t\t\t\t\"property\": {\n\t\t\t\t\t\t\t\t\t\"value\": \"twitterHandle\"\n\t\t\t\t\t\t\t\t},\n\t\t\t\t\t\t\t\t\"propertyInit\": {\n\t\t\t\t\t\t\t\t\t\"value\": \"\"\n\t\t\t\t\t\t\t\t},\n\t\t\t\t\t\t\t\t\"textIcon\": {\n\t\t\t\t\t\t\t\t\t\"value\": \"\"\n\t\t\t\t\t\t\t\t},\n\t\t\t\t\t\t\t\t\"textIconPosition\": {\n\t\t\t\t\t\t\t\t\t\"value\": \"left\"\n\t\t\t\t\t\t\t\t},\n\t\t\t\t\t\t\t\t\"textMinlength\": {\n\t\t\t\t\t\t\t\t\t\"value\": \"\"\n\t\t\t\t\t\t\t\t},\n\t\t\t\t\t\t\t\t\"textMaxlength\": {\n\t\t\t\t\t\t\t\t\t\"value\": \"\"\n\t\t\t\t\t\t\t\t},\n\t\t\t\t\t\t\t\t\"textPattern\": {\n\t\t\t\t\t\t\t\t\t\"value\": \"\"\n\t\t\t\t\t\t\t\t},\n\t\t\t\t\t\t\t\t\"textMask\": {\n\t\t\t\t\t\t\t\t\t\"value\": \"\"\n\t\t\t\t\t\t\t\t},\n\t\t\t\t\t\t\t\t\"textPlaceholder\": {\n\t\t\t\t\t\t\t\t\t\"value\": \"Enter a person's Twitter Handle such as BarackObama\"\n\t\t\t\t\t\t\t\t},\n\t\t\t\t\t\t\t\t\"textErrorMinlength\": {\n\t\t\t\t\t\t\t\t\t\"value\": \"\"\n\t\t\t\t\t\t\t\t},\n\t\t\t\t\t\t\t\t\"textErrorMaxlength\": {\n\t\t\t\t\t\t\t\t\t\"value\": \"\"\n\t\t\t\t\t\t\t\t},\n\t\t\t\t\t\t\t\t\"textErrorPattern\": {\n\t\t\t\t\t\t\t\t\t\"value\": \"\"\n\t\t\t\t\t\t\t\t},\n\t\t\t\t\t\t\t\t\"passwordIcon\": {\n\t\t\t\t\t\t\t\t\t\"value\": \"\"\n\t\t\t\t\t\t\t\t},\n\t\t\t\t\t\t\t\t\"passwordIconPosition\": {\n\t\t\t\t\t\t\t\t\t\"value\": \"left\"\n\t\t\t\t\t\t\t\t},\n\t\t\t\t\t\t\t\t\"passwordMinlength\": {\n\t\t\t\t\t\t\t\t\t\"value\": \"\"\n\t\t\t\t\t\t\t\t},\n\t\t\t\t\t\t\t\t\"passwordMaxlength\": {\n\t\t\t\t\t\t\t\t\t\"value\": \"\"\n\t\t\t\t\t\t\t\t},\n\t\t\t\t\t\t\t\t\"passwordErrorMinlength\": {\n\t\t\t\t\t\t\t\t\t\"value\": \"\"\n\t\t\t\t\t\t\t\t},\n\t\t\t\t\t\t\t\t\"passwordErrorMaxlength\": {\n\t\t\t\t\t\t\t\t\t\"value\": \"\"\n\t\t\t\t\t\t\t\t},\n\t\t\t\t\t\t\t\t\"dateFormat\": {\n\t\t\t\t\t\t\t\t\t\"value\": \"mm/dd/yyyy\"\n\t\t\t\t\t\t\t\t},\n\t\t\t\t\t\t\t\t\"dateMin\": {\n\t\t\t\t\t\t\t\t\t\"value\": \"\"\n\t\t\t\t\t\t\t\t},\n\t\t\t\t\t\t\t\t\"dateMax\": {\n\t\t\t\t\t\t\t\t\t\"value\": \"\"\n\t\t\t\t\t\t\t\t},\n\t\t\t\t\t\t\t\t\"dateErrorFormat\": {\n\t\t\t\t\t\t\t\t\t\"value\": \"\"\n\t\t\t\t\t\t\t\t},\n\t\t\t\t\t\t\t\t\"moneyIcon\": {\n\t\t\t\t\t\t\t\t\t\"value\": \"\"\n\t\t\t\t\t\t\t\t},\n\t\t\t\t\t\t\t\t\"moneyIconPosition\": {\n\t\t\t\t\t\t\t\t\t\"value\": \"left\"\n\t\t\t\t\t\t\t\t},\n\t\t\t\t\t\t\t\t\"moneyThousandSeparator\": {\n\t\t\t\t\t\t\t\t\t\"value\": \",\"\n\t\t\t\t\t\t\t\t},\n\t\t\t\t\t\t\t\t\"moneyDecimalSeparator\": {\n\t\t\t\t\t\t\t\t\t\"value\": \".\"\n\t\t\t\t\t\t\t\t},\n\t\t\t\t\t\t\t\t\"moneyNumberDigits\": {\n\t\t\t\t\t\t\t\t\t\"value\": \"2\"\n\t\t\t\t\t\t\t\t},\n\t\t\t\t\t\t\t\t\"numberIcon\": {\n\t\t\t\t\t\t\t\t\t\"value\": \"\"\n\t\t\t\t\t\t\t\t},\n\t\t\t\t\t\t\t\t\"numberIconPosition\": {\n\t\t\t\t\t\t\t\t\t\"value\": \"left\"\n\t\t\t\t\t\t\t\t},\n\t\t\t\t\t\t\t\t\"numberMin\": {\n\t\t\t\t\t\t\t\t\t\"value\": \"0\"\n\t\t\t\t\t\t\t\t},\n\t\t\t\t\t\t\t\t\"numberMax\": {\n\t\t\t\t\t\t\t\t\t\"value\": \"10\"\n\t\t\t\t\t\t\t\t},\n\t\t\t\t\t\t\t\t\"numberStep\": {\n\t\t\t\t\t\t\t\t\t\"value\": \"1\"\n\t\t\t\t\t\t\t\t},\n\t\t\t\t\t\t\t\t\"display\": {\n\t\t\t\t\t\t\t\t\t\"value\": \"true\"\n\t\t\t\t\t\t\t\t},\n\t\t\t\t\t\t\t\t\"disabled\": {\n\t\t\t\t\t\t\t\t\t\"value\": \"false\"\n\t\t\t\t\t\t\t\t},\n\t\t\t\t\t\t\t\t\"required\": {\n\t\t\t\t\t\t\t\t\t\"value\": \"no\"\n\t\t\t\t\t\t\t\t},\n\t\t\t\t\t\t\t\t\"errorRequired\": {\n\t\t\t\t\t\t\t\t\t\"value\": \"\"\n\t\t\t\t\t\t\t\t},\n\t\t\t\t\t\t\t\t\"containerClasses\": {\n\t\t\t\t\t\t\t\t\t\"value\": \"\"\n\t\t\t\t\t\t\t\t},\n\t\t\t\t\t\t\t\t\"containerDynamicClasses\": {\n\t\t\t\t\t\t\t\t\t\"value\": \"\"\n\t\t\t\t\t\t\t\t},\n\t\t\t\t\t\t\t\t\"containerCss\": {\n\t\t\t\t\t\t\t\t\t\"width\": \"60%\",\n\t\t\t\t\t\t\t\t\t\"height\": \"\",\n\t\t\t\t\t\t\t\t\t\"color\": \"\",\n\t\t\t\t\t\t\t\t\t\"background\": \"\",\n\t\t\t\t\t\t\t\t\t\"padding\": \"\",\n\t\t\t\t\t\t\t\t\t\"margin\": \"\",\n\t\t\t\t\t\t\t\t\t\"text-align\": \"\"\n\t\t\t\t\t\t\t\t},\n\t\t\t\t\t\t\t\t\"containerStyle\": {\n\t\t\t\t\t\t\t\t\t\"value\": \"\"\n\t\t\t\t\t\t\t\t},\n\t\t\t\t\t\t\t\t\"classes\": {\n\t\t\t\t\t\t\t\t\t\"value\": \"input-lg\"\n\t\t\t\t\t\t\t\t},\n\t\t\t\t\t\t\t\t\"dynamicClasses\": {\n\t\t\t\t\t\t\t\t\t\"value\": \"\"\n\t\t\t\t\t\t\t\t},\n\t\t\t\t\t\t\t\t\"css\": {\n\t\t\t\t\t\t\t\t\t\"width\": \"\",\n\t\t\t\t\t\t\t\t\t\"height\": \"\",\n\t\t\t\t\t\t\t\t\t\"color\": \"\",\n\t\t\t\t\t\t\t\t\t\"background\": \"\",\n\t\t\t\t\t\t\t\t\t\"padding\": \"\",\n\t\t\t\t\t\t\t\t\t\"margin\": \"\",\n\t\t\t\t\t\t\t\t\t\"text-align\": \"\"\n\t\t\t\t\t\t\t\t},\n\t\t\t\t\t\t\t\t\"style\": {\n\t\t\t\t\t\t\t\t\t\"value\": \"\"\n\t\t\t\t\t\t\t\t},\n\t\t\t\t\t\t\t\t\"onchange\": {\n\t\t\t\t\t\t\t\t\t\"value\": \"\"\n\t\t\t\t\t\t\t\t}\n\t\t\t\t\t\t\t},\n\t\t\t\t\t\t\t\"children\": [],\n\t\t\t\t\t\t\t\"container\": \"layout_0_row_0_column_0\"\n\t\t\t\t\t\t},\n\t\t\t\t\t\t{\n\t\t\t\t\t\t\t\"id\": 5129,\n\t\t\t\t\t\t\t\"type\": \"html\",\n\t\t\t\t\t\t\t\"attributes\": {\n\t\t\t\t\t\t\t\t\"name\": {\n\t\t\t\t\t\t\t\t\t\"value\": \"fieldTextArea1\"\n\t\t\t\t\t\t\t\t},\n\t\t\t\t\t\t\t\t\"html\": {\n\t\t\t\t\t\t\t\t\t\"value\": \"<font color=\\\"lightSkyBlue\\\"><i class=\\\"fa fa-twitter fa-3x pull-left fa-border\\\"></i></font> {{allTweets}} \"\n\t\t\t\t\t\t\t\t},\n\t\t\t\t\t\t\t\t\"property\": {\n\t\t\t\t\t\t\t\t\t\"value\": \"\"\n\t\t\t\t\t\t\t\t},\n\t\t\t\t\t\t\t\t\"display\": {\n\t\t\t\t\t\t\t\t\t\"value\": \"showDetail == true\"\n\t\t\t\t\t\t\t\t},\n\t\t\t\t\t\t\t\t\"containerClasses\": {\n\t\t\t\t\t\t\t\t\t\"value\": \"\"\n\t\t\t\t\t\t\t\t},\n\t\t\t\t\t\t\t\t\"containerDynamicClasses\": {\n\t\t\t\t\t\t\t\t\t\"value\": \"\"\n\t\t\t\t\t\t\t\t},\n\t\t\t\t\t\t\t\t\"containerCss\": {\n\t\t\t\t\t\t\t\t\t\"width\": \"100%\",\n\t\t\t\t\t\t\t\t\t\"height\": \"\",\n\t\t\t\t\t\t\t\t\t\"color\": \"\",\n\t\t\t\t\t\t\t\t\t\"background\": \"\",\n\t\t\t\t\t\t\t\t\t\"padding\": \"\",\n\t\t\t\t\t\t\t\t\t\"margin\": \"\",\n\t\t\t\t\t\t\t\t\t\"text-align\": \"\"\n\t\t\t\t\t\t\t\t},\n\t\t\t\t\t\t\t\t\"containerStyle\": {\n\t\t\t\t\t\t\t\t\t\"value\": \"\"\n\t\t\t\t\t\t\t\t},\n\t\t\t\t\t\t\t\t\"classes\": {\n\t\t\t\t\t\t\t\t\t\"value\": \"\"\n\t\t\t\t\t\t\t\t},\n\t\t\t\t\t\t\t\t\"dynamicClasses\": {\n\t\t\t\t\t\t\t\t\t\"value\": \"\"\n\t\t\t\t\t\t\t\t},\n\t\t\t\t\t\t\t\t\"css\": {\n\t\t\t\t\t\t\t\t\t\"width\": \"\",\n\t\t\t\t\t\t\t\t\t\"height\": \"\",\n\t\t\t\t\t\t\t\t\t\"color\": \"#c0c0c0\",\n\t\t\t\t\t\t\t\t\t\"background\": \"\",\n\t\t\t\t\t\t\t\t\t\"padding\": \"\",\n\t\t\t\t\t\t\t\t\t\"margin\": \"\",\n\t\t\t\t\t\t\t\t\t\"text-align\": \"\"\n\t\t\t\t\t\t\t\t},\n\t\t\t\t\t\t\t\t\"style\": {\n\t\t\t\t\t\t\t\t\t\"value\": \"\"\n\t\t\t\t\t\t\t\t},\n\t\t\t\t\t\t\t\t\"onclick\": {\n\t\t\t\t\t\t\t\t\t\"value\": \"\"\n\t\t\t\t\t\t\t\t}\n\t\t\t\t\t\t\t},\n\t\t\t\t\t\t\t\"children\": [],\n\t\t\t\t\t\t\t\"container\": \"layout_0_row_2_column_0\"\n\t\t\t\t\t\t},\n\t\t\t\t\t\t{\n\t\t\t\t\t\t\t\"id\": 46272,\n\t\t\t\t\t\t\t\"type\": \"statictext\",\n\t\t\t\t\t\t\t\"attributes\": {\n\t\t\t\t\t\t\t\t\"name\": {\n\t\t\t\t\t\t\t\t\t\"value\": \"txtText10\"\n\t\t\t\t\t\t\t\t},\n\t\t\t\t\t\t\t\t\"bind\": {\n\t\t\t\t\t\t\t\t\t\"value\": \"\"\n\t\t\t\t\t\t\t\t},\n\t\t\t\t\t\t\t\t\"text\": {\n\t\t\t\t\t\t\t\t\t\"value\": \"\"\n\t\t\t\t\t\t\t\t},\n\t\t\t\t\t\t\t\t\"display\": {\n\t\t\t\t\t\t\t\t\t\"value\": \"true\"\n\t\t\t\t\t\t\t\t},\n\t\t\t\t\t\t\t\t\"tooltip\": {\n\t\t\t\t\t\t\t\t\t\"value\": \"Personality Insight with IBM Watson\"\n\t\t\t\t\t\t\t\t},\n\t\t\t\t\t\t\t\t\"tooltipPosition\": {\n\t\t\t\t\t\t\t\t\t\"value\": \"bottom\"\n\t\t\t\t\t\t\t\t},\n\t\t\t\t\t\t\t\t\"counter\": {\n\t\t\t\t\t\t\t\t\t\"bind\": {\n\t\t\t\t\t\t\t\t\t\t\"value\": \"\"\n\t\t\t\t\t\t\t\t\t},\n\t\t\t\t\t\t\t\t\t\"onclick\": {\n\t\t\t\t\t\t\t\t\t\t\"value\": \"\"\n\t\t\t\t\t\t\t\t\t},\n\t\t\t\t\t\t\t\t\t\"position\": {\n\t\t\t\t\t\t\t\t\t\t\"value\": \"left\"\n\t\t\t\t\t\t\t\t\t}\n\t\t\t\t\t\t\t\t},\n\t\t\t\t\t\t\t\t\"onclick\": {\n\t\t\t\t\t\t\t\t\t\"value\": \"analyzeTwitterWatson()\"\n\t\t\t\t\t\t\t\t},\n\t\t\t\t\t\t\t\t\"classes\": {\n\t\t\t\t\t\t\t\t\t\"value\": \"boxStyle fa fa-twitter fa-5x\"\n\t\t\t\t\t\t\t\t},\n\t\t\t\t\t\t\t\t\"dynamicClasses\": {\n\t\t\t\t\t\t\t\t\t\"value\": \"\"\n\t\t\t\t\t\t\t\t},\n\t\t\t\t\t\t\t\t\"style\": {\n\t\t\t\t\t\t\t\t\t\"value\": \"\"\n\t\t\t\t\t\t\t\t},\n\t\t\t\t\t\t\t\t\"css\": {\n\t\t\t\t\t\t\t\t\t\"width\": \"100%\",\n\t\t\t\t\t\t\t\t\t\"height\": \"\",\n\t\t\t\t\t\t\t\t\t\"color\": \"\",\n\t\t\t\t\t\t\t\t\t\"background\": \"#87cefa\",\n\t\t\t\t\t\t\t\t\t\"padding\": \"20px\",\n\t\t\t\t\t\t\t\t\t\"margin\": \"20px 0px 20px 0px\",\n\t\t\t\t\t\t\t\t\t\"text-align\": \"center\"\n\t\t\t\t\t\t\t\t},\n\t\t\t\t\t\t\t\t\"containerClasses\": {\n\t\t\t\t\t\t\t\t\t\"value\": \"\"\n\t\t\t\t\t\t\t\t},\n\t\t\t\t\t\t\t\t\"containerDynamicClasses\": {\n\t\t\t\t\t\t\t\t\t\"value\": \"\"\n\t\t\t\t\t\t\t\t},\n\t\t\t\t\t\t\t\t\"containerStyle\": {\n\t\t\t\t\t\t\t\t\t\"value\": \"\"\n\t\t\t\t\t\t\t\t},\n\t\t\t\t\t\t\t\t\"containerCss\": {\n\t\t\t\t\t\t\t\t\t\"width\": \"120px\",\n\t\t\t\t\t\t\t\t\t\"height\": \"\",\n\t\t\t\t\t\t\t\t\t\"color\": \"\",\n\t\t\t\t\t\t\t\t\t\"background\": \"\",\n\t\t\t\t\t\t\t\t\t\"padding\": \"\",\n\t\t\t\t\t\t\t\t\t\"margin\": \"\",\n\t\t\t\t\t\t\t\t\t\"text-align\": \"\"\n\t\t\t\t\t\t\t\t}\n\t\t\t\t\t\t\t},\n\t\t\t\t\t\t\t\"children\": [],\n\t\t\t\t\t\t\t\"container\": \"layout_0_row_1_column_0\"\n\t\t\t\t\t\t},\n\t\t\t\t\t\t{\n\t\t\t\t\t\t\t\"id\": 89494,\n\t\t\t\t\t\t\t\"type\": \"statictext\",\n\t\t\t\t\t\t\t\"attributes\": {\n\t\t\t\t\t\t\t\t\"name\": {\n\t\t\t\t\t\t\t\t\t\"value\": \"txtText6\"\n\t\t\t\t\t\t\t\t},\n\t\t\t\t\t\t\t\t\"bind\": {\n\t\t\t\t\t\t\t\t\t\"value\": \"\"\n\t\t\t\t\t\t\t\t},\n\t\t\t\t\t\t\t\t\"text\": {\n\t\t\t\t\t\t\t\t\t\"value\": \"\"\n\t\t\t\t\t\t\t\t},\n\t\t\t\t\t\t\t\t\"display\": {\n\t\t\t\t\t\t\t\t\t\"value\": \"true\"\n\t\t\t\t\t\t\t\t},\n\t\t\t\t\t\t\t\t\"tooltip\": {\n\t\t\t\t\t\t\t\t\t\"value\": \"\"\n\t\t\t\t\t\t\t\t},\n\t\t\t\t\t\t\t\t\"tooltipPosition\": {\n\t\t\t\t\t\t\t\t\t\"value\": \"top\"\n\t\t\t\t\t\t\t\t},\n\t\t\t\t\t\t\t\t\"counter\": {\n\t\t\t\t\t\t\t\t\t\"bind\": {\n\t\t\t\t\t\t\t\t\t\t\"value\": \"\"\n\t\t\t\t\t\t\t\t\t},\n\t\t\t\t\t\t\t\t\t\"onclick\": {\n\t\t\t\t\t\t\t\t\t\t\"value\": \"\"\n\t\t\t\t\t\t\t\t\t},\n\t\t\t\t\t\t\t\t\t\"position\": {\n\t\t\t\t\t\t\t\t\t\t\"value\": \"left\"\n\t\t\t\t\t\t\t\t\t}\n\t\t\t\t\t\t\t\t},\n\t\t\t\t\t\t\t\t\"onclick\": {\n\t\t\t\t\t\t\t\t\t\"value\": \"navigate(1)\"\n\t\t\t\t\t\t\t\t},\n\t\t\t\t\t\t\t\t\"classes\": {\n\t\t\t\t\t\t\t\t\t\"value\": \"boxStyle fa fa-chevron-right fa-2x\"\n\t\t\t\t\t\t\t\t},\n\t\t\t\t\t\t\t\t\"dynamicClasses\": {\n\t\t\t\t\t\t\t\t\t\"value\": \"\"\n\t\t\t\t\t\t\t\t},\n\t\t\t\t\t\t\t\t\"style\": {\n\t\t\t\t\t\t\t\t\t\"value\": \"\"\n\t\t\t\t\t\t\t\t},\n\t\t\t\t\t\t\t\t\"css\": {\n\t\t\t\t\t\t\t\t\t\"width\": \"100%\",\n\t\t\t\t\t\t\t\t\t\"height\": \"\",\n\t\t\t\t\t\t\t\t\t\"color\": \"\",\n\t\t\t\t\t\t\t\t\t\"background\": \"#8fbc8f\",\n\t\t\t\t\t\t\t\t\t\"padding\": \"10px\",\n\t\t\t\t\t\t\t\t\t\"margin\": \"\",\n\t\t\t\t\t\t\t\t\t\"text-align\": \"center\"\n\t\t\t\t\t\t\t\t},\n\t\t\t\t\t\t\t\t\"containerClasses\": {\n\t\t\t\t\t\t\t\t\t\"value\": \"\"\n\t\t\t\t\t\t\t\t},\n\t\t\t\t\t\t\t\t\"containerDynamicClasses\": {\n\t\t\t\t\t\t\t\t\t\"value\": \"\"\n\t\t\t\t\t\t\t\t},\n\t\t\t\t\t\t\t\t\"containerStyle\": {\n\t\t\t\t\t\t\t\t\t\"value\": \"\"\n\t\t\t\t\t\t\t\t},\n\t\t\t\t\t\t\t\t\"containerCss\": {\n\t\t\t\t\t\t\t\t\t\"width\": \"120px\",\n\t\t\t\t\t\t\t\t\t\"height\": \"\",\n\t\t\t\t\t\t\t\t\t\"color\": \"\",\n\t\t\t\t\t\t\t\t\t\"background\": \"\",\n\t\t\t\t\t\t\t\t\t\"padding\": \"\",\n\t\t\t\t\t\t\t\t\t\"margin\": \"10px 0px 10px 0px\",\n\t\t\t\t\t\t\t\t\t\"text-align\": \"\"\n\t\t\t\t\t\t\t\t}\n\t\t\t\t\t\t\t},\n\t\t\t\t\t\t\t\"children\": [],\n\t\t\t\t\t\t\t\"container\": \"layout_0_row_0_column_0\"\n\t\t\t\t\t\t}\n\t\t\t\t\t],\n\t\t\t\t\t\"container\": \"layout_0_row_0_column_0\"\n\t\t\t\t}\n\t\t\t]\n\t\t}\n\t],\n\t\"resources\": [\n\t\t{\n\t\t\t\"name\": \"images\"\n\t\t}\n\t]\n}",
	"src_script": "// this line should not be removed\nvar wWatsonPI = angular.module( \"wWatsonPI\",[]);\n\nwWatsonPI.controller( \"wWatsonPIController\", function( $scope ) {\n    \n    \n    //---------------------- This code is executed the first time the widget is created --------------------------\n    $scope.showDetail = false;\n    $scope.currentIndex = -1;\n    $scope.sampleTwitterHandles = [ \"BarackObama\", \"markcuban\", \"sandycarter\", \"eminem\", \"beyonce\"];\n    \n    \n\n    //----------------- function that calls twitter then Watson and returns Personality Insights from Watson\n    $scope.analyzeTwitterWatson = function() { \n        \n        //first query returns concatinated response from twitter\n        var dq = new DataQuery( 'qTwitterConcat' );\n        dq.setParameters({\"screen_name\":$scope.twitterHandle});\n        dq.execute().\n        \tdone( function() {\n        \t\t$scope.$apply(function() {\n        \t\t\tvar tweets = dq.getData();\n        \t\t\t//removing special characters to make it a valid input for watson\n        \t\t\t$scope.allTweets = tweets[0].replace(/[^a-zA-Z ]/g, \"\");\n        \t\t\t\n        \t\t\t//defining request body of second watson query\n                    var second_body={\"contentItems\": [\n                        {\n                            \"id\": \"xxx\",\n                            \"userid\": \"abc\",\n                            \"sourceid\": \"twitter\",\n                            \"contenttype\": \"text/plain\",\n                            \"language\": \"en\",\n                            \"content\":$scope.allTweets\n                        }\n                    ]};\n                    \n                    //we are inside the first query and we will call the second watson query\n        \t\t\tvar dq1 = new DataQuery( 'qWatsonUserModeling' );\n        \t\t\tdq1.setReqBody(second_body);\n                    dq1.execute().\n                    \tdone( function() {\n                    \t\t$scope.$apply(function() {\n                    \t\t\t$scope.moods = dq1.getData().tree.children;\n                    \t\t\t//show the detail area once all data has been fetched\n                    \t\t\t$scope.showDetail = true;\n                    \t\t});\n                    \t});\n        \t\t});\n        \t});\n        };\n    //-------------- End function\n    \n    \n    //-------------- Change the index of the \"card\" to be shown\" and apply it to the \"model structure\" used by the GC\n    $scope.navigate = function(arg) {\n        \n        $scope.currentIndex = $scope.currentIndex + arg;\n        \n        if ($scope.currentIndex < 0) {\n            $scope.currentIndex = $scope.sampleTwitterHandles.length - 1;\n        } else if ($scope.currentIndex >= $scope.sampleTwitterHandles.length) {\n            $scope.currentIndex = 0 ;\n        }\n\n        $scope.twitterHandle = $scope.sampleTwitterHandles[$scope.currentIndex]; \n        \n        return '';\n    }; \n    //-------------- End function\n\n    \n    \n}); \n\n",
	"src_styles": ".floating {\n    float:left;\n}\n\n.trans_panel{\n    background-color:transparent\n}\n\n.boxStyle {\n  transition: color 0.5s ease;\n  color: black;\n}\n.boxStyle:hover {\n    color: white;\n}\n\n",
	"name": "wWatsonPI",
	"requestDate": "2015-02-19T19:13:50.474Z",
	"ownerId": "",
	"description": "An example of a modern layout",
	"category": "SamplesGallery",
	"platform": "web",
	"wtype": "visual",
	"versioning": {
		"my_dfx_db": {
			"last_action": "1425476307",
			"status": "committed",
			"user": "admin"
		},
		"SampleGallery": {
			"last_action": "1424701860",
			"status": "committed",
			"user": "admin"
		},
		"dreamface1": {
			"status": "modified",
			"user": "admin",
			"last_action": "1424373230"
		}
	}
}